Workbook
Name IQ_CH: 110000
Name IQ_CQ: 5000
Name IQ_CY: 10000
Name IQ_DAILY: 500000
Name IQ_FH: 100000
Name IQ_FQ: 500
Name IQ_FY: 1000
Name IQ_LTM: 2000
Name IQ_MONTH: 15000
Name IQ_NTM: 6000
Name IQ_WEEK: 50000
Name IQ_YTD: 3000
Name UPDATE: 'Raw Data Trent Ltd'!$E$1
Name UPDATE: #REF!

Sheet Historical IFS Trent Ltd
B2: ="Historical Financial Statements - "&'Raw Data Trent Ltd'!$B$1&"." -> Historical Financial Statements - TRENT LTD.
B3: Years | C3: ='Raw Data Trent Ltd'!B16 -> 42825 | D3: =C3+365 -> 43190 | E3: =D3+365 -> 43555 | F3: =E3+365 -> 43920 | G3: =F3+365 -> 44285 | H3: =G3+365 -> 44650 | I3: =H3+365 -> 45015 | J3: =I3+365 -> 45380 | K3: =J3+365 -> 45745 | L3: =K3+365 -> 46110 | M3: LTM
A5: # | B5: Income Statement
B6: Sales | C6: =IFERROR('Raw Data Trent Ltd'!B17,0) -> 1812.44 | D6: =IFERROR('Raw Data Trent Ltd'!C17,0) -> 2157.46 | E6: =IFERROR('Raw Data Trent Ltd'!D17,0) -> 2630.24 | F6: =IFERROR('Raw Data Trent Ltd'!E17,0) -> 3485.98 | G6: =IFERROR('Raw Data Trent Ltd'!F17,0) -> 2592.96 | H6: =IFERROR('Raw Data Trent Ltd'!G17,0) -> 4498.02 | I6: =IFERROR('Raw Data Trent Ltd'!H17,0) -> 8242.02 | J6: =IFERROR('Raw Data Trent Ltd'!I17,0) -> 12375.11 | ... L6: =IFERROR('Raw Data Trent Ltd'!K17,0) -> 20074.21 | M6: =IFERROR(SUM('Raw Data Trent Ltd'!H42:K42),0) -> 20074.21
B7: Sales Growth | D7: =(D6/C6)-1 -> 0.19036216 | E7: =(E6/D6)-1 -> 0.21913732 | F7: =(F6/E6)-1 -> 0.32534674 | G7: =(G6/F6)-1 -> -0.25617473 | H7: =(H6/G6)-1 -> 0.73470474 | I7: =(I6/H6)-1 -> 0.83236624 | J7: =(J6/I6)-1 -> 0.50146566 | K7: =(K6/J6)-1 -> 0.38460264 | ... M7: =(M6/L6)-1 -> 0
B9: COGS | C9: =IFERROR(SUM('Raw Data Trent Ltd'!B18,'Raw Data Trent Ltd'!B20:B22)-1*'Raw Data Trent Ltd'!B19,0) -> 1209.27 | D9: =IFERROR(SUM('Raw Data Trent Ltd'!C18,'Raw Data Trent Ltd'!C20:C22)-1*'Raw Data Trent Ltd'!C19,0) -> 1408.06 | E9: =IFERROR(SUM('Raw Data Trent Ltd'!D18,'Raw Data Trent Ltd'!D20:D22)-1*'Raw Data Trent Ltd'!D19,0) -> 1781.6 | F9: =IFERROR(SUM('Raw Data Trent Ltd'!E18,'Raw Data Trent Ltd'!E20:E22)-1*'Raw Data Trent Ltd'!E19,0) -> 2406.91 | G9: =IFERROR(SUM('Raw Data Trent Ltd'!F18,'Raw Data Trent Ltd'!F20:F22)-1*'Raw Data Trent Ltd'!F19,0) -> 1978.81 | H9: =IFERROR(SUM('Raw Data Trent Ltd'!G18,'Raw Data Trent Ltd'!G20:G22)-1*'Raw Data Trent Ltd'!G19,0) -> 3083.49 | I9: =IFERROR(SUM('Raw Data Trent Ltd'!H18,'Raw Data Trent Ltd'!H20:H22)-1*'Raw Data Trent Ltd'!H19,0) -> 5735.08 | J9: =IFERROR(SUM('Raw Data Trent Ltd'!I18,'Raw Data Trent Ltd'!I20:I22)-1*'Raw Data Trent Ltd'!I19,0) -> 8494.38 | ... L9: =IFERROR(SUM('Raw Data Trent Ltd'!K18,'Raw Data Trent Ltd'!K20:K22)-1*'Raw Data Trent Ltd'!K19,0) -> 12620.2 | M9: =IFERROR(SUM('Raw Data Trent Ltd'!H43:K43),0) -> 16418
B10: COGS % Sales | C10: =C9/C6 -> 0.66720554 | D10: =D9/D6 -> 0.65264709 | E10: =E9/E6 -> 0.67735264 | F10: =F9/F6 -> 0.69045433 | G10: =G9/G6 -> 0.76314714 | H10: =H9/H6 -> 0.68552163 | I10: =I9/I6 -> 0.69583427 | J10: =J9/J6 -> 0.68640844 | ... M10: =M9/M6 -> 0.81786531
B12: Gross Profit | C12: =C6-C9 -> 603.17 | D12: =D6-D9 -> 749.4 | E12: =E6-E9 -> 848.64 | F12: =F6-F9 -> 1079.07 | G12: =G6-G9 -> 614.15 | H12: =H6-H9 -> 1414.53 | I12: =I6-I9 -> 2506.94 | J12: =J6-J9 -> 3880.73 | ... M12: =M6-M9 -> 3656.21
B13: GP % Sales | C13: =C12/C6 -> 0.33279446 | D13: =D12/D6 -> 0.34735291 | E13: =E12/E6 -> 0.32264736 | F13: =F12/F6 -> 0.30954567 | G13: =G12/G6 -> 0.23685286 | H13: =H12/H6 -> 0.31447837 | I13: =I12/I6 -> 0.30416573 | J13: =J12/J6 -> 0.31359156 | ... M13: =M12/M6 -> 0.18213469
B15: Selling & General Expenses | C15: =IFERROR(SUM('Raw Data Trent Ltd'!B23:B24),0) -> 469.64 | D15: =IFERROR(SUM('Raw Data Trent Ltd'!C23:C24),0) -> 540.9 | E15: =IFERROR(SUM('Raw Data Trent Ltd'!D23:D24),0) -> 608 | F15: =IFERROR(SUM('Raw Data Trent Ltd'!E23:E24),0) -> 550.1 | G15: =IFERROR(SUM('Raw Data Trent Ltd'!F23:F24),0) -> 500.28 | H15: =IFERROR(SUM('Raw Data Trent Ltd'!G23:G24),0) -> 819.81 | I15: =IFERROR(SUM('Raw Data Trent Ltd'!H23:H24),0) -> 1392.79 | J15: =IFERROR(SUM('Raw Data Trent Ltd'!I23:I24),0) -> 1910.04 | ... L15: =IFERROR(SUM('Raw Data Trent Ltd'!K23:K24),0) -> 3780.62
B16: S&G Exp % Sales | C16: =C15/C6 -> 0.2591203 | D16: =D15/D6 -> 0.25071148 | E16: =E15/E6 -> 0.23115761 | F16: =F15/F6 -> 0.15780354 | G16: =G15/G6 -> 0.1929378 | H16: =H15/H6 -> 0.18226019 | I16: =I15/I6 -> 0.16898649 | J16: =J15/J6 -> 0.15434529 | ... L16: =L15/L6 -> 0.18833219
B18: EBITDA | C18: =C12-C15 -> 133.53 | D18: =D12-D15 -> 208.5 | E18: =E12-E15 -> 240.64 | F18: =F12-F15 -> 528.97 | G18: =G12-G15 -> 113.87 | H18: =H12-H15 -> 594.72 | I18: =I12-I15 -> 1114.15 | J18: =J12-J15 -> 1970.69 | ... L18: =L12-L15 -> 3673.39 | M18: =IFERROR(SUM('Raw Data Trent Ltd'!H51:K51),0) -> 3764.34
B19: EBITDA % Sales | C19: =C18/C6 -> 0.073674163 | D19: =D18/D6 -> 0.096641421 | E19: =E18/E6 -> 0.09148975 | F19: =F18/F6 -> 0.15174212 | G19: =G18/G6 -> 0.043915062 | H19: =H18/H6 -> 0.13221818 | I19: =I18/I6 -> 0.13517924 | J19: =J18/J6 -> 0.15924626 | ... M19: =M18/M6 -> 0.1875212
B21: Interest | C21: =IFERROR('Raw Data Trent Ltd'!B27,0) -> 45.55 | D21: =IFERROR('Raw Data Trent Ltd'!C27,0) -> 43.78 | E21: =IFERROR('Raw Data Trent Ltd'!D27,0) -> 50.64 | F21: =IFERROR('Raw Data Trent Ltd'!E27,0) -> 263.37 | G21: =IFERROR('Raw Data Trent Ltd'!F27,0) -> 260.79 | H21: =IFERROR('Raw Data Trent Ltd'!G27,0) -> 324.84 | I21: =IFERROR('Raw Data Trent Ltd'!H27,0) -> 408.99 | J21: =IFERROR('Raw Data Trent Ltd'!I27,0) -> 367.66 | ... L21: =IFERROR('Raw Data Trent Ltd'!K27,0) -> 168.35 | M21: =IFERROR(SUM('Raw Data Trent Ltd'!H46:K46),0) -> 168.35
B22: Interest % Sales | C22: =C21/C6 -> 0.025131866 | D22: =D21/D6 -> 0.020292381 | E22: =E21/E6 -> 0.019252996 | F22: =F21/F6 -> 0.075551208 | G22: =G21/G6 -> 0.10057618 | H22: =H21/H6 -> 0.072218443 | I22: =I21/I6 -> 0.049622544 | J22: =J21/J6 -> 0.029709635 | ... M22: =M21/M6 -> 0.0083863823
B24: Depriciation | C24: =IFERROR('Raw Data Trent Ltd'!B26,0) -> 41.29 | D24: =IFERROR('Raw Data Trent Ltd'!C26,0) -> 45.53 | E24: =IFERROR('Raw Data Trent Ltd'!D26,0) -> 51.67 | F24: =IFERROR('Raw Data Trent Ltd'!E26,0) -> 247.24 | G24: =IFERROR('Raw Data Trent Ltd'!F26,0) -> 257.3 | H24: =IFERROR('Raw Data Trent Ltd'!G26,0) -> 310.82 | I24: =IFERROR('Raw Data Trent Ltd'!H26,0) -> 493.69 | J24: =IFERROR('Raw Data Trent Ltd'!I26,0) -> 671.11 | ... L24: =IFERROR('Raw Data Trent Ltd'!K26,0) -> 1361.19 | M24: =IFERROR(SUM('Raw Data Trent Ltd'!H45:K45),0) -> 1361.19
B25: Deprication % Sales | C25: =C24/C6 -> 0.022781444 | D25: =D24/D6 -> 0.02110352 | E25: =E24/E6 -> 0.019644595 | F25: =F24/F6 -> 0.070924102 | G25: =G24/G6 -> 0.099230223 | H25: =H24/H6 -> 0.069101516 | I25: =I24/I6 -> 0.059899151 | J25: =J24/J6 -> 0.054230629 | ... M25: =M24/M6 -> 0.067807899
B27: Earnings before Tax | C27: =IFERROR(C18-SUM(C21,C24),0) -> 46.69 | D27: =IFERROR(D18-SUM(D21,D24),0) -> 119.19 | E27: =IFERROR(E18-SUM(E21,E24),0) -> 138.33 | F27: =IFERROR(F18-SUM(F21,F24),0) -> 18.36 | G27: =IFERROR(G18-SUM(G21,G24),0) -> -404.22 | H27: =IFERROR(H18-SUM(H21,H24),0) -> -40.94 | I27: =IFERROR(I18-SUM(I21,I24),0) -> 211.47 | J27: =IFERROR(J18-SUM(J21,J24),0) -> 931.92 | ... M27: =IFERROR(M18-SUM(M21,M24),0) -> 2234.8
B28: EBT % Sales | C28: =C27/C6 -> 0.025760853 | D28: =D27/D6 -> 0.05524552 | E28: =E27/E6 -> 0.052592159 | F28: =F27/F6 -> 0.0052668116 | G28: =G27/G6 -> -0.15589134 | H28: =H27/H6 -> -0.0091017826 | I28: =I27/I6 -> 0.025657545 | J28: =J27/J6 -> 0.075305997 | ... M28: =M27/M6 -> 0.11132692
B30: Tax | C30: =IFERROR('Raw Data Trent Ltd'!B29,0) -> 43.05 | D30: =IFERROR('Raw Data Trent Ltd'!C29,0) -> 59.62 | E30: =IFERROR('Raw Data Trent Ltd'!D29,0) -> 73.61 | F30: =IFERROR('Raw Data Trent Ltd'!E29,0) -> 59.01 | G30: =IFERROR('Raw Data Trent Ltd'!F29,0) -> -23.69 | H30: =IFERROR('Raw Data Trent Ltd'!G29,0) -> 76.62 | I30: =IFERROR('Raw Data Trent Ltd'!H29,0) -> 158.44 | J30: =IFERROR('Raw Data Trent Ltd'!I29,0) -> 443.37 | ... L30: =IFERROR('Raw Data Trent Ltd'!K29,0) -> 515.15 | M30: =IFERROR(SUM('Raw Data Trent Ltd'!H48:K48),0) -> 515.15
B31: Effective Tax Rate | C31: =C30/C27 -> 0.92203898 | D31: =D30/D27 -> 0.50020975 | E31: =E30/E27 -> 0.5321333 | F31: =F30/F27 -> 3.2140523 | G31: =G30/G27 -> 0.058606699 | H31: =H30/H27 -> -1.8715193 | I31: =I30/I27 -> 0.74923157 | J31: =J30/J27 -> 0.47575972 | ... M31: =M30/M27 -> 0.2305128
B33: Net Profit | C33: =IFERROR(C27-C30,0) -> 3.64 | D33: =IFERROR(D27-D30,0) -> 59.57 | E33: =IFERROR(E27-E30,0) -> 64.72 | F33: =IFERROR(F27-F30,0) -> -40.65 | G33: =IFERROR(G27-G30,0) -> -380.53 | H33: =IFERROR(H27-H30,0) -> -117.56 | I33: =IFERROR(I27-I30,0) -> 53.03 | J33: =IFERROR(J27-J30,0) -> 488.55 | ... M33: =IFERROR(M27-M30,0) -> 1719.65
B34: Net Margin | C34: =C33/C6 -> 0.0020083423 | D34: =D33/D6 -> 0.027611172 | E34: =E33/E6 -> 0.02460612 | F34: =F33/F6 -> -0.011660996 | G34: =G33/G6 -> -0.14675506 | H34: =H33/H6 -> -0.026135944 | I34: =I33/I6 -> 0.0064341023 | J34: =J33/J6 -> 0.039478437 | ... M34: =M33/M6 -> 0.085664641
B36: No of Equity Share | C36: =IFERROR('Raw Data Trent Ltd'!B93,0) -> 33.23 | D36: =IFERROR('Raw Data Trent Ltd'!C93,0) -> 33.23 | E36: =IFERROR('Raw Data Trent Ltd'!D93,0) -> 33.23 | F36: =IFERROR('Raw Data Trent Ltd'!E93,0) -> 35.55 | G36: =IFERROR('Raw Data Trent Ltd'!F93,0) -> 35.55 | H36: =IFERROR('Raw Data Trent Ltd'!G93,0) -> 35.55 | I36: =IFERROR('Raw Data Trent Ltd'!H93,0) -> 35.55 | J36: =IFERROR('Raw Data Trent Ltd'!I93,0) -> 35.55 | ... M36: =IFERROR('Raw Data Trent Ltd'!L93,0) -> 0
B38: EPS | C38: =C33/C36 -> 0.10953957 | D38: =D33/D36 -> 1.7926572 | E38: =E33/E36 -> 1.9476377 | F38: =F33/F36 -> -1.1434599 | G38: =G33/G36 -> -10.704079 | H38: =H33/H36 -> -3.3068917 | I38: =I33/I36 -> 1.4917018 | J38: =J33/J36 -> 13.742616 | ... L38: =L33/L36 -> 45.814346 | M38: =IFERROR(M33/M36,0) -> 0
B39: EPS Growth % | D39: =(D38/C38)-1 -> 15.365385 | E39: =(E38/D38)-1 -> 0.086452913 | F39: =(F38/E38)-1 -> -1.5871009 | G39: =(G38/F38)-1 -> 8.3611316 | H39: =(H38/G38)-1 -> -0.69106247 | I39: =(I38/H38)-1 -> -1.4510888 | J39: =(J38/I38)-1 -> 8.2127098 | K39: =(K38/J38)-1 -> 1.5163238 | ... M39: =(M38/L38)-1 -> -1
B41: Dividend per Share | C41: =IFERROR('Raw Data Trent Ltd'!B31/C36,0) -> 1 | D41: =IFERROR('Raw Data Trent Ltd'!C31/D36,0) -> 1.1498646 | E41: =IFERROR('Raw Data Trent Ltd'!D31/E36,0) -> 1.3000301 | F41: =IFERROR('Raw Data Trent Ltd'!E31/F36,0) -> 1 | G41: =IFERROR('Raw Data Trent Ltd'!F31/G36,0) -> 0.6 | H41: =IFERROR('Raw Data Trent Ltd'!G31/H36,0) -> 1.7001406 | I41: =IFERROR('Raw Data Trent Ltd'!H31/I36,0) -> 2.2 | J41: =IFERROR('Raw Data Trent Ltd'!I31/J36,0) -> 3.2 | ... M41: =IFERROR('Raw Data Trent Ltd'!L31/M36,0) -> 0
B42: Divident Payout Ratio % | C42: =IFERROR(C41/C38,0) -> 9.1291209 | D42: =IFERROR(D41/D38,0) -> 0.64143025 | E42: =IFERROR(E41/E38,0) -> 0.66749073 | F42: =IFERROR(F41/F38,0) -> -0.87453875 | G42: =IFERROR(G41/G38,0) -> -0.056053399 | H42: =IFERROR(H41/H38,0) -> -0.51412045 | I42: =IFERROR(I41/I38,0) -> 1.4748256 | J42: =IFERROR(J41/J38,0) -> 0.23285232 | ... M42: =IFERROR(M41/M38,0) -> 0
B44: Retained Earnings | C44: =IFERROR(IF(C38>C41,1-C42,0),0) -> 0 | D44: =IFERROR(IF(D38>D41,1-D42,0),0) -> 0.35856975 | E44: =IFERROR(IF(E38>E41,1-E42,0),0) -> 0.33250927 | F44: =IFERROR(IF(F38>F41,1-F42,0),0) -> 0 | G44: =IFERROR(IF(G38>G41,1-G42,0),0) -> 0 | H44: =IFERROR(IF(H38>H41,1-H42,0),0) -> 0 | I44: =IFERROR(IF(I38>I41,1-I42,0),0) -> 0 | J44: =IFERROR(IF(J38>J41,1-J42,0),0) -> 0.76714768 | ... M44: =IFERROR(IF(M38>M41,1-M42,0),0) -> 0
A46: # | B46: Balace Sheet
B47: Equity Share Capital | C47: =IFERROR('Raw Data Trent Ltd'!B57,0) -> 33.23 | D47: =IFERROR('Raw Data Trent Ltd'!C57,0) -> 33.23 | E47: =IFERROR('Raw Data Trent Ltd'!D57,0) -> 33.23 | F47: =IFERROR('Raw Data Trent Ltd'!E57,0) -> 35.55 | G47: =IFERROR('Raw Data Trent Ltd'!F57,0) -> 35.55 | H47: =IFERROR('Raw Data Trent Ltd'!G57,0) -> 35.55 | I47: =IFERROR('Raw Data Trent Ltd'!H57,0) -> 35.55 | J47: =IFERROR('Raw Data Trent Ltd'!I57,0) -> 35.55 | ... L47: =IFERROR('Raw Data Trent Ltd'!K57,0) -> 35.55
B48: Reserves | C48: =IFERROR('Raw Data Trent Ltd'!B58,0) -> 1514.46 | D48: =IFERROR('Raw Data Trent Ltd'!C58,0) -> 1562.14 | E48: =IFERROR('Raw Data Trent Ltd'!D58,0) -> 1613.28 | F48: =IFERROR('Raw Data Trent Ltd'!E58,0) -> 2352.22 | G48: =IFERROR('Raw Data Trent Ltd'!F58,0) -> 2277.48 | H48: =IFERROR('Raw Data Trent Ltd'!G58,0) -> 2328.45 | I48: =IFERROR('Raw Data Trent Ltd'!H58,0) -> 2559.94 | J48: =IFERROR('Raw Data Trent Ltd'!I58,0) -> 4032.19 | ... L48: =IFERROR('Raw Data Trent Ltd'!K58,0) -> 6949.13
B49: Borrowings | C49: =IFERROR('Raw Data Trent Ltd'!B59,0) -> 391.74 | D49: =IFERROR('Raw Data Trent Ltd'!C59,0) -> 391.43 | E49: =IFERROR('Raw Data Trent Ltd'!D59,0) -> 494.14 | F49: =IFERROR('Raw Data Trent Ltd'!E59,0) -> 299.74 | G49: =IFERROR('Raw Data Trent Ltd'!F59,0) -> 2963.63 | H49: =IFERROR('Raw Data Trent Ltd'!G59,0) -> 4725.36 | I49: =IFERROR('Raw Data Trent Ltd'!H59,0) -> 4464.14 | J49: =IFERROR('Raw Data Trent Ltd'!I59,0) -> 1752.99 | ... L49: =IFERROR('Raw Data Trent Ltd'!K59,0) -> 2561.25
B50: Other Liabilities | C50: =IFERROR('Raw Data Trent Ltd'!B60,0) -> 282.82 | D50: =IFERROR('Raw Data Trent Ltd'!C60,0) -> 349.06 | E50: =IFERROR('Raw Data Trent Ltd'!D60,0) -> 418.11 | F50: =IFERROR('Raw Data Trent Ltd'!E60,0) -> 2819.17 | G50: =IFERROR('Raw Data Trent Ltd'!F60,0) -> 447.07 | H50: =IFERROR('Raw Data Trent Ltd'!G60,0) -> 636.66 | I50: =IFERROR('Raw Data Trent Ltd'!H60,0) -> 1021.9 | J50: =IFERROR('Raw Data Trent Ltd'!I60,0) -> 1341.02 | ... L50: =IFERROR('Raw Data Trent Ltd'!K60,0) -> 2182.65
B51: Total Liablity | C51: =SUM(C47:C50) -> 2222.25 | D51: =SUM(D47:D50) -> 2335.86 | E51: =SUM(E47:E50) -> 2558.76 | F51: =SUM(F47:F50) -> 5506.68 | G51: =SUM(G47:G50) -> 5723.73 | H51: =SUM(H47:H50) -> 7726.02 | I51: =SUM(I47:I50) -> 8081.53 | J51: =SUM(J47:J50) -> 7161.75 | ... L51: =SUM(L47:L50) -> 11728.58
B53: Fixed Asset Net Block | C53: =IFERROR('Raw Data Trent Ltd'!B62,0) -> 548.71 | D53: =IFERROR('Raw Data Trent Ltd'!C62,0) -> 612.53 | E53: =IFERROR('Raw Data Trent Ltd'!D62,0) -> 662.18 | F53: =IFERROR('Raw Data Trent Ltd'!E62,0) -> 2738.43 | G53: =IFERROR('Raw Data Trent Ltd'!F62,0) -> 3053.82 | H53: =IFERROR('Raw Data Trent Ltd'!G62,0) -> 4686.71 | I53: =IFERROR('Raw Data Trent Ltd'!H62,0) -> 4526.95 | J53: =IFERROR('Raw Data Trent Ltd'!I62,0) -> 2449.92 | ... L53: =IFERROR('Raw Data Trent Ltd'!K62,0) -> 5518.74
B54: Capital Work in Progress | C54: =IFERROR('Raw Data Trent Ltd'!B63,0) -> 5.48 | D54: =IFERROR('Raw Data Trent Ltd'!C63,0) -> 9.59 | E54: =IFERROR('Raw Data Trent Ltd'!D63,0) -> 87.18 | F54: =IFERROR('Raw Data Trent Ltd'!E63,0) -> 23.32 | G54: =IFERROR('Raw Data Trent Ltd'!F63,0) -> 107.98 | H54: =IFERROR('Raw Data Trent Ltd'!G63,0) -> 104.72 | I54: =IFERROR('Raw Data Trent Ltd'!H63,0) -> 101.72 | J54: =IFERROR('Raw Data Trent Ltd'!I63,0) -> 223.78 | ... L54: =IFERROR('Raw Data Trent Ltd'!K63,0) -> 253.99
B55: Investments | C55: =IFERROR('Raw Data Trent Ltd'!B64,0) -> 1079.96 | D55: =IFERROR('Raw Data Trent Ltd'!C64,0) -> 1022.88 | E55: =IFERROR('Raw Data Trent Ltd'!D64,0) -> 882.83 | F55: =IFERROR('Raw Data Trent Ltd'!E64,0) -> 1514.78 | G55: =IFERROR('Raw Data Trent Ltd'!F64,0) -> 1487.29 | H55: =IFERROR('Raw Data Trent Ltd'!G64,0) -> 1283.72 | I55: =IFERROR('Raw Data Trent Ltd'!H64,0) -> 1109.87 | J55: =IFERROR('Raw Data Trent Ltd'!I64,0) -> 1416.03 | ... L55: =IFERROR('Raw Data Trent Ltd'!K64,0) -> 1384.91
B56: Other Assets | C56: ='Raw Data Trent Ltd'!B75 -> 242.54 | D56: ='Raw Data Trent Ltd'!C75 -> 298.18 | E56: ='Raw Data Trent Ltd'!D75 -> 358.79 | F56: ='Raw Data Trent Ltd'!E75 -> 543.81 | G56: ='Raw Data Trent Ltd'!F75 -> 544.01 | H56: ='Raw Data Trent Ltd'!G75 -> 678.86 | I56: ='Raw Data Trent Ltd'!H75 -> 861.14 | J56: ='Raw Data Trent Ltd'!I75 -> 1109.99 | ... L56: ='Raw Data Trent Ltd'!K75 -> 1947.79
B57: Total Non Current Assets | C57: =IFERROR(SUM(C53:C56),0) -> 1876.69 | D57: =IFERROR(SUM(D53:D56),0) -> 1943.18 | E57: =IFERROR(SUM(E53:E56),0) -> 1990.98 | F57: =IFERROR(SUM(F53:F56),0) -> 4820.34 | G57: =IFERROR(SUM(G53:G56),0) -> 5193.1 | H57: =IFERROR(SUM(H53:H56),0) -> 6754.01 | I57: =IFERROR(SUM(I53:I56),0) -> 6599.68 | J57: =IFERROR(SUM(J53:J56),0) -> 5199.72 | ... L57: =IFERROR(SUM(L53:L56),0) -> 9105.43
B59: Receivables | C59: =IFERROR('Raw Data Trent Ltd'!B67,0) -> 5.92 | D59: =IFERROR('Raw Data Trent Ltd'!C67,0) -> 15.1 | E59: =IFERROR('Raw Data Trent Ltd'!D67,0) -> 16.54 | F59: =IFERROR('Raw Data Trent Ltd'!E67,0) -> 17.12 | G59: =IFERROR('Raw Data Trent Ltd'!F67,0) -> 20.77 | H59: =IFERROR('Raw Data Trent Ltd'!G67,0) -> 18.26 | I59: =IFERROR('Raw Data Trent Ltd'!H67,0) -> 34.39 | J59: =IFERROR('Raw Data Trent Ltd'!I67,0) -> 81.74 | ... L59: =IFERROR('Raw Data Trent Ltd'!K67,0) -> 51.14
B60: Inventory | C60: =IFERROR('Raw Data Trent Ltd'!B68,0) -> 305.36 | D60: =IFERROR('Raw Data Trent Ltd'!C68,0) -> 344.77 | E60: =IFERROR('Raw Data Trent Ltd'!D68,0) -> 497.01 | F60: =IFERROR('Raw Data Trent Ltd'!E68,0) -> 607.81 | G60: =IFERROR('Raw Data Trent Ltd'!F68,0) -> 428.39 | H60: =IFERROR('Raw Data Trent Ltd'!G68,0) -> 867.78 | I60: =IFERROR('Raw Data Trent Ltd'!H68,0) -> 1361.16 | J60: =IFERROR('Raw Data Trent Ltd'!I68,0) -> 1582.73 | ... L60: =IFERROR('Raw Data Trent Ltd'!K68,0) -> 2289.01
B61: Cash & Bank | C61: =IFERROR('Raw Data Trent Ltd'!B69,0) -> 34.28 | D61: =IFERROR('Raw Data Trent Ltd'!C69,0) -> 32.81 | E61: =IFERROR('Raw Data Trent Ltd'!D69,0) -> 54.23 | F61: =IFERROR('Raw Data Trent Ltd'!E69,0) -> 61.41 | G61: =IFERROR('Raw Data Trent Ltd'!F69,0) -> 81.47 | H61: =IFERROR('Raw Data Trent Ltd'!G69,0) -> 85.97 | I61: =IFERROR('Raw Data Trent Ltd'!H69,0) -> 86.3 | J61: =IFERROR('Raw Data Trent Ltd'!I69,0) -> 297.56 | ... L61: =IFERROR('Raw Data Trent Ltd'!K69,0) -> 283
B62: Total Current Assets | C62: =IFERROR(SUM(C59:C61),0) -> 345.56 | D62: =IFERROR(SUM(D59:D61),0) -> 392.68 | E62: =IFERROR(SUM(E59:E61),0) -> 567.78 | F62: =IFERROR(SUM(F59:F61),0) -> 686.34 | G62: =IFERROR(SUM(G59:G61),0) -> 530.63 | H62: =IFERROR(SUM(H59:H61),0) -> 972.01 | I62: =IFERROR(SUM(I59:I61),0) -> 1481.85 | J62: =IFERROR(SUM(J59:J61),0) -> 1962.03 | ... L62: =IFERROR(SUM(L59:L61),0) -> 2623.15
B64: Total Asset | C64: =IFERROR(SUM(C62,C57),0) -> 2222.25 | D64: =IFERROR(SUM(D62,D57),0) -> 2335.86 | E64: =IFERROR(SUM(E62,E57),0) -> 2558.76 | F64: =IFERROR(SUM(F62,F57),0) -> 5506.68 | G64: =IFERROR(SUM(G62,G57),0) -> 5723.73 | H64: =IFERROR(SUM(H62,H57),0) -> 7726.02 | I64: =IFERROR(SUM(I62,I57),0) -> 8081.53 | J64: =IFERROR(SUM(J62,J57),0) -> 7161.75 | ... L64: =IFERROR(SUM(L62,L57),0) -> 11728.58
B66: Check | C66: =IF(C64=C51,"OK","Fault") -> OK | D66: =IF(D64=D51,"OK","Fault") -> OK | E66: =IF(E64=E51,"OK","Fault") -> OK | F66: =IF(F64=F51,"OK","Fault") -> OK | G66: =IF(G64=G51,"OK","Fault") -> OK | H66: =IF(H64=H51,"OK","Fault") -> OK | I66: =IF(I64=I51,"OK","Fault") -> OK | J66: =IF(J64=J51,"OK","Fault") -> OK | ... L66: =IF(L64=L51,"OK","Fault") -> OK
A68: # | B68: Cash Flow
B69: Operating Activities
B70: ='Raw Data CF Trent Ltd'!B4 -> Profit from operations | C70: =IFERROR('Raw Data CF Trent Ltd'!E4,0) -> 165 | D70: =IFERROR('Raw Data CF Trent Ltd'!F4,0) -> 191 | E70: =IFERROR('Raw Data CF Trent Ltd'!G4,0) -> 233 | F70: =IFERROR('Raw Data CF Trent Ltd'!H4,0) -> 542 | G70: =IFERROR('Raw Data CF Trent Ltd'!I4,0) -> 180 | H70: =IFERROR('Raw Data CF Trent Ltd'!J4,0) -> 569 | I70: =IFERROR('Raw Data CF Trent Ltd'!K4,0) -> 1079 | J70: =IFERROR('Raw Data CF Trent Ltd'!L4,0) -> 1919 | ... L70: =IFERROR('Raw Data CF Trent Ltd'!N4,0) -> 3618
B71: ='Raw Data CF Trent Ltd'!B5 -> Receivables | C71: =IFERROR('Raw Data CF Trent Ltd'!E5,0) -> 24 | D71: =IFERROR('Raw Data CF Trent Ltd'!F5,0) -> -54 | E71: =IFERROR('Raw Data CF Trent Ltd'!G5,0) -> -11 | F71: =IFERROR('Raw Data CF Trent Ltd'!H5,0) -> -20 | G71: =IFERROR('Raw Data CF Trent Ltd'!I5,0) -> -39 | H71: =IFERROR('Raw Data CF Trent Ltd'!J5,0) -> -103 | I71: =IFERROR('Raw Data CF Trent Ltd'!K5,0) -> -101 | J71: =IFERROR('Raw Data CF Trent Ltd'!L5,0) -> -208 | ... L71: =IFERROR('Raw Data CF Trent Ltd'!N5,0) -> -196
B72: ='Raw Data CF Trent Ltd'!B6 -> Inventory | C72: =IFERROR('Raw Data CF Trent Ltd'!E6,0) -> -26 | D72: =IFERROR('Raw Data CF Trent Ltd'!F6,0) -> -39 | E72: =IFERROR('Raw Data CF Trent Ltd'!G6,0) -> -152 | F72: =IFERROR('Raw Data CF Trent Ltd'!H6,0) -> -89 | G72: =IFERROR('Raw Data CF Trent Ltd'!I6,0) -> 179 | H72: =IFERROR('Raw Data CF Trent Ltd'!J6,0) -> -439 | I72: =IFERROR('Raw Data CF Trent Ltd'!K6,0) -> -494 | J72: =IFERROR('Raw Data CF Trent Ltd'!L6,0) -> -222 | ... L72: =IFERROR('Raw Data CF Trent Ltd'!N6,0) -> -243
B73: ='Raw Data CF Trent Ltd'!B7 -> Payables | C73: =IFERROR('Raw Data CF Trent Ltd'!E7,0) -> -9 | D73: =IFERROR('Raw Data CF Trent Ltd'!F7,0) -> 43 | E73: =IFERROR('Raw Data CF Trent Ltd'!G7,0) -> 49 | F73: =IFERROR('Raw Data CF Trent Ltd'!H7,0) -> 26 | G73: =IFERROR('Raw Data CF Trent Ltd'!I7,0) -> -11 | H73: =IFERROR('Raw Data CF Trent Ltd'!J7,0) -> 134 | I73: =IFERROR('Raw Data CF Trent Ltd'!K7,0) -> 332 | J73: =IFERROR('Raw Data CF Trent Ltd'!L7,0) -> 178 | ... L73: =IFERROR('Raw Data CF Trent Ltd'!N7,0) -> 311
B74: ='Raw Data CF Trent Ltd'!B8 -> Loans Advances | C74: =IFERROR('Raw Data CF Trent Ltd'!E8,0) -> 0 | D74: =IFERROR('Raw Data CF Trent Ltd'!F8,0) -> 0 | E74: =IFERROR('Raw Data CF Trent Ltd'!G8,0) -> 0 | F74: =IFERROR('Raw Data CF Trent Ltd'!H8,0) -> 0 | G74: =IFERROR('Raw Data CF Trent Ltd'!I8,0) -> 0 | H74: =IFERROR('Raw Data CF Trent Ltd'!J8,0) -> 0 | I74: =IFERROR('Raw Data CF Trent Ltd'!K8,0) -> 0 | J74: =IFERROR('Raw Data CF Trent Ltd'!L8,0) -> 0 | ... L74: =IFERROR('Raw Data CF Trent Ltd'!N8,0) -> -288
B75: ='Raw Data CF Trent Ltd'!B9 -> Other WC items | C75: =IFERROR('Raw Data CF Trent Ltd'!E9,0) -> -12 | D75: =IFERROR('Raw Data CF Trent Ltd'!F9,0) -> -13 | E75: =IFERROR('Raw Data CF Trent Ltd'!G9,0) -> -21 | F75: =IFERROR('Raw Data CF Trent Ltd'!H9,0) -> -15 | G75: =IFERROR('Raw Data CF Trent Ltd'!I9,0) -> -23 | H75: =IFERROR('Raw Data CF Trent Ltd'!J9,0) -> -22 | I75: =IFERROR('Raw Data CF Trent Ltd'!K9,0) -> -30 | J75: =IFERROR('Raw Data CF Trent Ltd'!L9,0) -> -20 | ... L75: =IFERROR('Raw Data CF Trent Ltd'!N9,0) -> 17
B76: Working Capital Changes 1 | C76: =SUM(C71:C75) -> -23 | D76: =SUM(D71:D75) -> -63 | E76: =SUM(E71:E75) -> -135 | F76: =SUM(F71:F75) -> -98 | G76: =SUM(G71:G75) -> 106 | H76: =SUM(H71:H75) -> -430 | I76: =SUM(I71:I75) -> -293 | J76: =SUM(J71:J75) -> -272 | ... L76: =SUM(L71:L75) -> -399
B77: ='Raw Data CF Trent Ltd'!B11 -> Direct taxes | C77: =IFERROR('Raw Data CF Trent Ltd'!E11,0) -> -38 | D77: =IFERROR('Raw Data CF Trent Ltd'!F11,0) -> -50 | E77: =IFERROR('Raw Data CF Trent Ltd'!G11,0) -> -77 | F77: =IFERROR('Raw Data CF Trent Ltd'!H11,0) -> -83 | G77: =IFERROR('Raw Data CF Trent Ltd'!I11,0) -> -1 | H77: =IFERROR('Raw Data CF Trent Ltd'!J11,0) -> -82 | I77: =IFERROR('Raw Data CF Trent Ltd'!K11,0) -> -191 | J77: =IFERROR('Raw Data CF Trent Ltd'!L11,0) -> -299 | ... L77: =IFERROR('Raw Data CF Trent Ltd'!N11,0) -> -551
B78: CFO | C78: =C70+C76+C77 -> 104 | D78: =D70+D76+D77 -> 78 | E78: =E70+E76+E77 -> 21 | F78: =F70+F76+F77 -> 361 | G78: =G70+G76+G77 -> 285 | H78: =H70+H76+H77 -> 57 | I78: =I70+I76+I77 -> 595 | J78: =J70+J76+J77 -> 1348 | ... L78: =L70+L76+L77 -> 2668
B80: Investing Activity
B81: ='Raw Data CF Trent Ltd'!B13 -> Fixed assets purchased | C81: =IFERROR('Raw Data CF Trent Ltd'!E13,0) -> -71 | D81: =IFERROR('Raw Data CF Trent Ltd'!F13,0) -> -107 | E81: =IFERROR('Raw Data CF Trent Ltd'!G13,0) -> -203 | F81: =IFERROR('Raw Data CF Trent Ltd'!H13,0) -> -156 | G81: =IFERROR('Raw Data CF Trent Ltd'!I13,0) -> -113 | H81: =IFERROR('Raw Data CF Trent Ltd'!J13,0) -> -271 | I81: =IFERROR('Raw Data CF Trent Ltd'!K13,0) -> -503 | J81: =IFERROR('Raw Data CF Trent Ltd'!L13,0) -> -737 | ... L81: =IFERROR('Raw Data CF Trent Ltd'!N13,0) -> -1763
B82: ='Raw Data CF Trent Ltd'!B14 -> Fixed assets sold | C82: =IFERROR('Raw Data CF Trent Ltd'!E14,0) -> 2 | D82: =IFERROR('Raw Data CF Trent Ltd'!F14,0) -> 1 | E82: =IFERROR('Raw Data CF Trent Ltd'!G14,0) -> 7 | F82: =IFERROR('Raw Data CF Trent Ltd'!H14,0) -> 42 | G82: =IFERROR('Raw Data CF Trent Ltd'!I14,0) -> 22 | H82: =IFERROR('Raw Data CF Trent Ltd'!J14,0) -> 61 | I82: =IFERROR('Raw Data CF Trent Ltd'!K14,0) -> 280 | J82: =IFERROR('Raw Data CF Trent Ltd'!L14,0) -> 343 | ... L82: =IFERROR('Raw Data CF Trent Ltd'!N14,0) -> 26
B83: ='Raw Data CF Trent Ltd'!B15 -> Investments purchased | C83: =IFERROR('Raw Data CF Trent Ltd'!E15,0) -> -937 | D83: =IFERROR('Raw Data CF Trent Ltd'!F15,0) -> -972 | E83: =IFERROR('Raw Data CF Trent Ltd'!G15,0) -> -1285 | F83: =IFERROR('Raw Data CF Trent Ltd'!H15,0) -> -2895 | G83: =IFERROR('Raw Data CF Trent Ltd'!I15,0) -> -591 | H83: =IFERROR('Raw Data CF Trent Ltd'!J15,0) -> -1322 | I83: =IFERROR('Raw Data CF Trent Ltd'!K15,0) -> -1610 | J83: =IFERROR('Raw Data CF Trent Ltd'!L15,0) -> -1938 | ... L83: =IFERROR('Raw Data CF Trent Ltd'!N15,0) -> -4825
B84: ='Raw Data CF Trent Ltd'!B16 -> Investments sold | C84: =IFERROR('Raw Data CF Trent Ltd'!E16,0) -> 951 | D84: =IFERROR('Raw Data CF Trent Ltd'!F16,0) -> 1065 | E84: =IFERROR('Raw Data CF Trent Ltd'!G16,0) -> 1510 | F84: =IFERROR('Raw Data CF Trent Ltd'!H16,0) -> 2237 | G84: =IFERROR('Raw Data CF Trent Ltd'!I16,0) -> 731 | H84: =IFERROR('Raw Data CF Trent Ltd'!J16,0) -> 1530 | I84: =IFERROR('Raw Data CF Trent Ltd'!K16,0) -> 1616 | J84: =IFERROR('Raw Data CF Trent Ltd'!L16,0) -> 1808 | ... L84: =IFERROR('Raw Data CF Trent Ltd'!N16,0) -> 4863
B85: ='Raw Data CF Trent Ltd'!B17 -> Interest received | C85: =IFERROR('Raw Data CF Trent Ltd'!E17,0) -> 17 | D85: =IFERROR('Raw Data CF Trent Ltd'!F17,0) -> 16 | E85: =IFERROR('Raw Data CF Trent Ltd'!G17,0) -> 16 | F85: =IFERROR('Raw Data CF Trent Ltd'!H17,0) -> 19 | G85: =IFERROR('Raw Data CF Trent Ltd'!I17,0) -> 21 | H85: =IFERROR('Raw Data CF Trent Ltd'!J17,0) -> 15 | I85: =IFERROR('Raw Data CF Trent Ltd'!K17,0) -> 8 | J85: =IFERROR('Raw Data CF Trent Ltd'!L17,0) -> 2 | ... L85: =IFERROR('Raw Data CF Trent Ltd'!N17,0) -> 17
B86: ='Raw Data CF Trent Ltd'!B18 -> Dividends received | C86: =IFERROR('Raw Data CF Trent Ltd'!E18,0) -> 2 | D86: =IFERROR('Raw Data CF Trent Ltd'!F18,0) -> 1 | E86: =IFERROR('Raw Data CF Trent Ltd'!G18,0) -> 2 | F86: =IFERROR('Raw Data CF Trent Ltd'!H18,0) -> 15 | G86: =IFERROR('Raw Data CF Trent Ltd'!I18,0) -> 5 | H86: =IFERROR('Raw Data CF Trent Ltd'!J18,0) -> 109 | I86: =IFERROR('Raw Data CF Trent Ltd'!K18,0) -> 148 | J86: =IFERROR('Raw Data CF Trent Ltd'!L18,0) -> 75 | ... L86: =IFERROR('Raw Data CF Trent Ltd'!N18,0) -> 34
B87: ='Raw Data CF Trent Ltd'!B19 -> Invest in subsidiaries | C87: =IFERROR('Raw Data CF Trent Ltd'!E19,0) -> 0 | D87: =IFERROR('Raw Data CF Trent Ltd'!F19,0) -> 0 | E87: =IFERROR('Raw Data CF Trent Ltd'!G19,0) -> 0 | F87: =IFERROR('Raw Data CF Trent Ltd'!H19,0) -> 0 | G87: =IFERROR('Raw Data CF Trent Ltd'!I19,0) -> 0 | H87: =IFERROR('Raw Data CF Trent Ltd'!J19,0) -> 0 | I87: =IFERROR('Raw Data CF Trent Ltd'!K19,0) -> 0 | J87: =IFERROR('Raw Data CF Trent Ltd'!L19,0) -> 0 | ... L87: =IFERROR('Raw Data CF Trent Ltd'!N19,0) -> -92
B88: ='Raw Data CF Trent Ltd'!B20 -> Redemp n Canc of Shares | C88: =IFERROR('Raw Data CF Trent Ltd'!E20,0) -> 0 | D88: =IFERROR('Raw Data CF Trent Ltd'!F20,0) -> 0 | E88: =IFERROR('Raw Data CF Trent Ltd'!G20,0) -> 0 | F88: =IFERROR('Raw Data CF Trent Ltd'!H20,0) -> 0 | G88: =IFERROR('Raw Data CF Trent Ltd'!I20,0) -> 0 | H88: =IFERROR('Raw Data CF Trent Ltd'!J20,0) -> 0 | I88: =IFERROR('Raw Data CF Trent Ltd'!K20,0) -> 0 | J88: =IFERROR('Raw Data CF Trent Ltd'!L20,0) -> 0 | ... L88: =IFERROR('Raw Data CF Trent Ltd'!N20,0) -> 146
B89: ='Raw Data CF Trent Ltd'!B21 -> Acquisition of companies | C89: =IFERROR('Raw Data CF Trent Ltd'!E21,0) -> -8 | D89: =IFERROR('Raw Data CF Trent Ltd'!F21,0) -> -7 | E89: =IFERROR('Raw Data CF Trent Ltd'!G21,0) -> -85 | F89: =IFERROR('Raw Data CF Trent Ltd'!H21,0) -> -22 | G89: =IFERROR('Raw Data CF Trent Ltd'!I21,0) -> -45 | H89: =IFERROR('Raw Data CF Trent Ltd'!J21,0) -> -66 | I89: =IFERROR('Raw Data CF Trent Ltd'!K21,0) -> -52 | J89: =IFERROR('Raw Data CF Trent Ltd'!L21,0) -> -62 | ... L89: =IFERROR('Raw Data CF Trent Ltd'!N21,0) -> 0
B90: ='Raw Data CF Trent Ltd'!B22 -> Other investing items | C90: =IFERROR('Raw Data CF Trent Ltd'!E22,0) -> 0 | D90: =IFERROR('Raw Data CF Trent Ltd'!F22,0) -> 0 | E90: =IFERROR('Raw Data CF Trent Ltd'!G22,0) -> 0 | F90: =IFERROR('Raw Data CF Trent Ltd'!H22,0) -> -49 | G90: =IFERROR('Raw Data CF Trent Ltd'!I22,0) -> -12 | H90: =IFERROR('Raw Data CF Trent Ltd'!J22,0) -> 0 | I90: =IFERROR('Raw Data CF Trent Ltd'!K22,0) -> 10 | J90: =IFERROR('Raw Data CF Trent Ltd'!L22,0) -> 0 | ... L90: =IFERROR('Raw Data CF Trent Ltd'!N22,0) -> 15
B91: CFI | C91: =IFERROR(SUM(C81:C90),0) -> -44 | D91: =IFERROR(SUM(D81:D90),0) -> -3 | E91: =IFERROR(SUM(E81:E90),0) -> -38 | F91: =IFERROR(SUM(F81:F90),0) -> -809 | G91: =IFERROR(SUM(G81:G90),0) -> 18 | H91: =IFERROR(SUM(H81:H90),0) -> 56 | I91: =IFERROR(SUM(I81:I90),0) -> -103 | J91: =IFERROR(SUM(J81:J90),0) -> -509 | ... L91: =IFERROR(SUM(L81:L90),0) -> -1579
B93: Financing Activity
B94: ='Raw Data CF Trent Ltd'!B24 -> Proceeds from shares | C94: =IFERROR('Raw Data CF Trent Ltd'!E24,0) -> 100 | D94: =IFERROR('Raw Data CF Trent Ltd'!F24,0) -> 0 | E94: =IFERROR('Raw Data CF Trent Ltd'!G24,0) -> 0 | F94: =IFERROR('Raw Data CF Trent Ltd'!H24,0) -> 1032 | G94: =IFERROR('Raw Data CF Trent Ltd'!I24,0) -> 0 | H94: =IFERROR('Raw Data CF Trent Ltd'!J24,0) -> 551 | I94: =IFERROR('Raw Data CF Trent Ltd'!K24,0) -> 46 | J94: =IFERROR('Raw Data CF Trent Ltd'!L24,0) -> 36 | ... L94: =IFERROR('Raw Data CF Trent Ltd'!N24,0) -> 0
B95: ='Raw Data CF Trent Ltd'!B25 -> Proceeds from borrowings | C95: =IFERROR('Raw Data CF Trent Ltd'!E25,0) -> 238 | D95: =IFERROR('Raw Data CF Trent Ltd'!F25,0) -> 382 | E95: =IFERROR('Raw Data CF Trent Ltd'!G25,0) -> 392 | F95: =IFERROR('Raw Data CF Trent Ltd'!H25,0) -> 93 | G95: =IFERROR('Raw Data CF Trent Ltd'!I25,0) -> 0 | H95: =IFERROR('Raw Data CF Trent Ltd'!J25,0) -> 0 | I95: =IFERROR('Raw Data CF Trent Ltd'!K25,0) -> 173 | J95: =IFERROR('Raw Data CF Trent Ltd'!L25,0) -> 0 | ... L95: =IFERROR('Raw Data CF Trent Ltd'!N25,0) -> 0
B96: ='Raw Data CF Trent Ltd'!B26 -> Repayment of borrowings | C96: =IFERROR('Raw Data CF Trent Ltd'!E26,0) -> -48 | D96: =IFERROR('Raw Data CF Trent Ltd'!F26,0) -> -282 | E96: =IFERROR('Raw Data CF Trent Ltd'!G26,0) -> -286 | F96: =IFERROR('Raw Data CF Trent Ltd'!H26,0) -> -186 | G96: =IFERROR('Raw Data CF Trent Ltd'!I26,0) -> 0 | H96: =IFERROR('Raw Data CF Trent Ltd'!J26,0) -> -301 | I96: =IFERROR('Raw Data CF Trent Ltd'!K26,0) -> -173 | J96: =IFERROR('Raw Data CF Trent Ltd'!L26,0) -> 0 | ... L96: =IFERROR('Raw Data CF Trent Ltd'!N26,0) -> 0
B97: ='Raw Data CF Trent Ltd'!B27 -> Interest paid fin | C97: =IFERROR('Raw Data CF Trent Ltd'!E27,0) -> -36 | D97: =IFERROR('Raw Data CF Trent Ltd'!F27,0) -> -32 | E97: =IFERROR('Raw Data CF Trent Ltd'!G27,0) -> -23 | F97: =IFERROR('Raw Data CF Trent Ltd'!H27,0) -> -251 | G97: =IFERROR('Raw Data CF Trent Ltd'!I27,0) -> -184 | H97: =IFERROR('Raw Data CF Trent Ltd'!J27,0) -> -246 | I97: =IFERROR('Raw Data CF Trent Ltd'!K27,0) -> -359 | J97: =IFERROR('Raw Data CF Trent Ltd'!L27,0) -> -309 | ... L97: =IFERROR('Raw Data CF Trent Ltd'!N27,0) -> -173
B98: ='Raw Data CF Trent Ltd'!B28 -> Dividends paid | C98: =IFERROR('Raw Data CF Trent Ltd'!E28,0) -> -1 | D98: =IFERROR('Raw Data CF Trent Ltd'!F28,0) -> -40 | E98: =IFERROR('Raw Data CF Trent Ltd'!G28,0) -> -46 | F98: =IFERROR('Raw Data CF Trent Ltd'!H28,0) -> -52 | G98: =IFERROR('Raw Data CF Trent Ltd'!I28,0) -> -36 | H98: =IFERROR('Raw Data CF Trent Ltd'!J28,0) -> -43 | I98: =IFERROR('Raw Data CF Trent Ltd'!K28,0) -> -39 | J98: =IFERROR('Raw Data CF Trent Ltd'!L28,0) -> -78 | ... L98: =IFERROR('Raw Data CF Trent Ltd'!N28,0) -> -177
B99: ='Raw Data CF Trent Ltd'!B29 -> Financial liabilities | C99: =IFERROR('Raw Data CF Trent Ltd'!E29,0) -> 0 | D99: =IFERROR('Raw Data CF Trent Ltd'!F29,0) -> 0 | E99: =IFERROR('Raw Data CF Trent Ltd'!G29,0) -> 0 | F99: =IFERROR('Raw Data CF Trent Ltd'!H29,0) -> -84 | G99: =IFERROR('Raw Data CF Trent Ltd'!I29,0) -> -63 | H99: =IFERROR('Raw Data CF Trent Ltd'!J29,0) -> -69 | I99: =IFERROR('Raw Data CF Trent Ltd'!K29,0) -> -140 | J99: =IFERROR('Raw Data CF Trent Ltd'!L29,0) -> -277 | ... L99: =IFERROR('Raw Data CF Trent Ltd'!N29,0) -> -797
B100: ='Raw Data CF Trent Ltd'!B30 -> Other financing items | C100: =IFERROR('Raw Data CF Trent Ltd'!E30,0) -> -303 | D100: =IFERROR('Raw Data CF Trent Ltd'!F30,0) -> -102 | E100: =IFERROR('Raw Data CF Trent Ltd'!G30,0) -> 0 | F100: =IFERROR('Raw Data CF Trent Ltd'!H30,0) -> -100 | G100: =IFERROR('Raw Data CF Trent Ltd'!I30,0) -> 0 | H100: =IFERROR('Raw Data CF Trent Ltd'!J30,0) -> 0 | I100: =IFERROR('Raw Data CF Trent Ltd'!K30,0) -> 0 | J100: =IFERROR('Raw Data CF Trent Ltd'!L30,0) -> 0 | ... L100: =IFERROR('Raw Data CF Trent Ltd'!N30,0) -> 0
B101: CFF | C101: =IFERROR(SUM(C94:C100),0) -> -50 | D101: =IFERROR(SUM(D94:D100),0) -> -74 | E101: =IFERROR(SUM(E94:E100),0) -> 37 | F101: =IFERROR(SUM(F94:F100),0) -> 452 | G101: =IFERROR(SUM(G94:G100),0) -> -283 | H101: =IFERROR(SUM(H94:H100),0) -> -108 | I101: =IFERROR(SUM(I94:I100),0) -> -492 | J101: =IFERROR(SUM(J94:J100),0) -> -628 | ... L101: =IFERROR(SUM(L94:L100),0) -> -1147
B103: Net Cash Flow | C103: =IFERROR(SUM(C101,C91,C78),0) -> 10 | D103: =IFERROR(SUM(D101,D91,D78),0) -> 1 | E103: =IFERROR(SUM(E101,E91,E78),0) -> 20 | F103: =IFERROR(SUM(F101,F91,F78),0) -> 4 | G103: =IFERROR(SUM(G101,G91,G78),0) -> 20 | H103: =IFERROR(SUM(H101,H91,H78),0) -> 5 | I103: =IFERROR(SUM(I101,I91,I78),0) -> 0 | J103: =IFERROR(SUM(J101,J91,J78),0) -> 211 | ... L103: =IFERROR(SUM(L101,L91,L78),0) -> -58
B105: Note:
B106: =" 1." -> 1. | C106: Working Capital Changes = Receivables + Inventory + Payables + Loans & Advances + Other WC

Sheet CommonSize Statement Trent Ltd 
B2: ="Common Size Income Statement"&" "&"-"&" "&'Raw Data Trent Ltd'!B1 -> Common Size Income Statement - TRENT LTD
B3: Particulars | C3: ='Raw Data Trent Ltd'!$B$16 -> 42825 | D3: =C3+365 -> 43190 | E3: =D3+365 -> 43555 | F3: =E3+365 -> 43920 | G3: =F3+365 -> 44285 | H3: =G3+365 -> 44650 | I3: =H3+365 -> 45015 | J3: =I3+365 -> 45380 | K3: =J3+365 -> 45745 | L3: =K3+365 -> 46110
B4: ='Raw Data Trent Ltd'!A17 -> Sales | C4: ='Raw Data Trent Ltd'!B17/'Raw Data Trent Ltd'!B$17 -> 1 | D4: ='Raw Data Trent Ltd'!C17/'Raw Data Trent Ltd'!C$17 -> 1 | E4: ='Raw Data Trent Ltd'!D17/'Raw Data Trent Ltd'!D$17 -> 1 | F4: ='Raw Data Trent Ltd'!E17/'Raw Data Trent Ltd'!E$17 -> 1 | G4: ='Raw Data Trent Ltd'!F17/'Raw Data Trent Ltd'!F$17 -> 1 | H4: ='Raw Data Trent Ltd'!G17/'Raw Data Trent Ltd'!G$17 -> 1 | I4: ='Raw Data Trent Ltd'!H17/'Raw Data Trent Ltd'!H$17 -> 1 | J4: ='Raw Data Trent Ltd'!I17/'Raw Data Trent Ltd'!I$17 -> 1 | ... L4: ='Raw Data Trent Ltd'!K17/'Raw Data Trent Ltd'!K$17 -> 1
B5: ='Raw Data Trent Ltd'!A18 -> Raw Material Cost | C5: ='Raw Data Trent Ltd'!B18/'Raw Data Trent Ltd'!B$17 -> 0.50275871 | D5: ='Raw Data Trent Ltd'!C18/'Raw Data Trent Ltd'!C$17 -> 0.49596285 | E5: ='Raw Data Trent Ltd'!D18/'Raw Data Trent Ltd'!D$17 -> 0.55495696 | F5: ='Raw Data Trent Ltd'!E18/'Raw Data Trent Ltd'!E$17 -> 0.55985404 | G5: ='Raw Data Trent Ltd'!F18/'Raw Data Trent Ltd'!F$17 -> 0.52898618 | H5: ='Raw Data Trent Ltd'!G18/'Raw Data Trent Ltd'!G$17 -> 0.64925901 | I5: ='Raw Data Trent Ltd'!H18/'Raw Data Trent Ltd'!H$17 -> 0.63225399 | J5: ='Raw Data Trent Ltd'!I18/'Raw Data Trent Ltd'!I$17 -> 0.57563933 | ... L5: ='Raw Data Trent Ltd'!K18/'Raw Data Trent Ltd'!K$17 -> 0.57271942
B6: ='Raw Data Trent Ltd'!A19 -> Change in Inventory | C6: ='Raw Data Trent Ltd'!B19/'Raw Data Trent Ltd'!B$17 -> 0.016475028 | D6: ='Raw Data Trent Ltd'!C19/'Raw Data Trent Ltd'!C$17 -> 0.017849694 | E6: ='Raw Data Trent Ltd'!D19/'Raw Data Trent Ltd'!D$17 -> 0.056356074 | F6: ='Raw Data Trent Ltd'!E19/'Raw Data Trent Ltd'!E$17 -> 0.020048882 | G6: ='Raw Data Trent Ltd'!F19/'Raw Data Trent Ltd'!F$17 -> -0.062615698 | H6: ='Raw Data Trent Ltd'!G19/'Raw Data Trent Ltd'!G$17 -> 0.097562928 | I6: ='Raw Data Trent Ltd'!H19/'Raw Data Trent Ltd'!H$17 -> 0.059610387 | J6: ='Raw Data Trent Ltd'!I19/'Raw Data Trent Ltd'!I$17 -> 0.013309781 | ... L6: ='Raw Data Trent Ltd'!K19/'Raw Data Trent Ltd'!K$17 -> 0.011566084
B7: ='Raw Data Trent Ltd'!A20 -> Power and Fuel | C7: ='Raw Data Trent Ltd'!B20/'Raw Data Trent Ltd'!B$17 -> 0.02829335 | D7: ='Raw Data Trent Ltd'!C20/'Raw Data Trent Ltd'!C$17 -> 0.024450048 | E7: ='Raw Data Trent Ltd'!D20/'Raw Data Trent Ltd'!D$17 -> 0.022499848 | F7: ='Raw Data Trent Ltd'!E20/'Raw Data Trent Ltd'!E$17 -> 0.019116576 | G7: ='Raw Data Trent Ltd'!F20/'Raw Data Trent Ltd'!F$17 -> 0.019055442 | H7: ='Raw Data Trent Ltd'!G20/'Raw Data Trent Ltd'!G$17 -> 0.015982588 | I7: ='Raw Data Trent Ltd'!H20/'Raw Data Trent Ltd'!H$17 -> 0.017505417 | J7: ='Raw Data Trent Ltd'!I20/'Raw Data Trent Ltd'!I$17 -> 0.018517815 | ... L7: ='Raw Data Trent Ltd'!K20/'Raw Data Trent Ltd'!K$17 -> 0
B8: ='Raw Data Trent Ltd'!A21 -> Other Mfr. Exp | C8: ='Raw Data Trent Ltd'!B21/'Raw Data Trent Ltd'!B$17 -> 0.04519322 | D8: ='Raw Data Trent Ltd'!C21/'Raw Data Trent Ltd'!C$17 -> 0.042077258 | E8: ='Raw Data Trent Ltd'!D21/'Raw Data Trent Ltd'!D$17 -> 0.046417817 | F8: ='Raw Data Trent Ltd'!E21/'Raw Data Trent Ltd'!E$17 -> 0.027972048 | G8: ='Raw Data Trent Ltd'!F21/'Raw Data Trent Ltd'!F$17 -> 0.035480686 | H8: ='Raw Data Trent Ltd'!G21/'Raw Data Trent Ltd'!G$17 -> 0.02826577 | I8: ='Raw Data Trent Ltd'!H21/'Raw Data Trent Ltd'!H$17 -> 0.025720636 | J8: ='Raw Data Trent Ltd'!I21/'Raw Data Trent Ltd'!I$17 -> 0.02138082 | ... L8: ='Raw Data Trent Ltd'!K21/'Raw Data Trent Ltd'!K$17 -> 0
B9: ='Raw Data Trent Ltd'!A22 -> Employee Cost | C9: ='Raw Data Trent Ltd'!B22/'Raw Data Trent Ltd'!B$17 -> 0.10743528 | D9: ='Raw Data Trent Ltd'!C22/'Raw Data Trent Ltd'!C$17 -> 0.10800664 | E9: ='Raw Data Trent Ltd'!D22/'Raw Data Trent Ltd'!D$17 -> 0.10983408 | F9: ='Raw Data Trent Ltd'!E22/'Raw Data Trent Ltd'!E$17 -> 0.10356055 | G9: ='Raw Data Trent Ltd'!F22/'Raw Data Trent Ltd'!F$17 -> 0.11700913 | H9: ='Raw Data Trent Ltd'!G22/'Raw Data Trent Ltd'!G$17 -> 0.089577192 | I9: ='Raw Data Trent Ltd'!H22/'Raw Data Trent Ltd'!H$17 -> 0.07996462 | J9: ='Raw Data Trent Ltd'!I22/'Raw Data Trent Ltd'!I$17 -> 0.084180262 | ... L9: ='Raw Data Trent Ltd'!K22/'Raw Data Trent Ltd'!K$17 -> 0.067523952
B10: ='Raw Data Trent Ltd'!A23 -> Selling and admin | C10: ='Raw Data Trent Ltd'!B23/'Raw Data Trent Ltd'!B$17 -> 0.22459778 | D10: ='Raw Data Trent Ltd'!C23/'Raw Data Trent Ltd'!C$17 -> 0.20886135 | E10: ='Raw Data Trent Ltd'!D23/'Raw Data Trent Ltd'!D$17 -> 0.19557531 | F10: ='Raw Data Trent Ltd'!E23/'Raw Data Trent Ltd'!E$17 -> 0.12530766 | G10: ='Raw Data Trent Ltd'!F23/'Raw Data Trent Ltd'!F$17 -> 0.14061922 | H10: ='Raw Data Trent Ltd'!G23/'Raw Data Trent Ltd'!G$17 -> 0.1567423 | I10: ='Raw Data Trent Ltd'!H23/'Raw Data Trent Ltd'!H$17 -> 0.15196881 | J10: ='Raw Data Trent Ltd'!I23/'Raw Data Trent Ltd'!I$17 -> 0.13814423 | ... L10: ='Raw Data Trent Ltd'!K23/'Raw Data Trent Ltd'!K$17 -> 0.077907923
B11: ='Raw Data Trent Ltd'!A24 -> Other Expenses | C11: ='Raw Data Trent Ltd'!B24/'Raw Data Trent Ltd'!B$17 -> 0.034522522 | D11: ='Raw Data Trent Ltd'!C24/'Raw Data Trent Ltd'!C$17 -> 0.041850139 | E11: ='Raw Data Trent Ltd'!D24/'Raw Data Trent Ltd'!D$17 -> 0.035582304 | F11: ='Raw Data Trent Ltd'!E24/'Raw Data Trent Ltd'!E$17 -> 0.032495884 | G11: ='Raw Data Trent Ltd'!F24/'Raw Data Trent Ltd'!F$17 -> 0.052318586 | H11: ='Raw Data Trent Ltd'!G24/'Raw Data Trent Ltd'!G$17 -> 0.025517895 | I11: ='Raw Data Trent Ltd'!H24/'Raw Data Trent Ltd'!H$17 -> 0.017017673 | J11: ='Raw Data Trent Ltd'!I24/'Raw Data Trent Ltd'!I$17 -> 0.016201068 | ... L11: ='Raw Data Trent Ltd'!K24/'Raw Data Trent Ltd'!K$17 -> 0.11042427
B12: ='Raw Data Trent Ltd'!A25 -> Other Income | C12: ='Raw Data Trent Ltd'!B25/'Raw Data Trent Ltd'!B$17 -> 0.044862175 | D12: ='Raw Data Trent Ltd'!C25/'Raw Data Trent Ltd'!C$17 -> 0.012732565 | E12: ='Raw Data Trent Ltd'!D25/'Raw Data Trent Ltd'!D$17 -> 0.01145903 | F12: ='Raw Data Trent Ltd'!E25/'Raw Data Trent Ltd'!E$17 -> 0.042062777 | G12: ='Raw Data Trent Ltd'!F25/'Raw Data Trent Ltd'!F$17 -> 0.076900531 | H12: ='Raw Data Trent Ltd'!G25/'Raw Data Trent Ltd'!G$17 -> 0.033828218 | I12: ='Raw Data Trent Ltd'!H25/'Raw Data Trent Ltd'!H$17 -> 0.041324821 | J12: ='Raw Data Trent Ltd'!I25/'Raw Data Trent Ltd'!I$17 -> 0.079911209 | ... L12: ='Raw Data Trent Ltd'!K25/'Raw Data Trent Ltd'!K$17 -> 0.0046143783
B13: ='Raw Data Trent Ltd'!A26 -> Depreciation | C13: ='Raw Data Trent Ltd'!B26/'Raw Data Trent Ltd'!B$17 -> 0.022781444 | D13: ='Raw Data Trent Ltd'!C26/'Raw Data Trent Ltd'!C$17 -> 0.02110352 | E13: ='Raw Data Trent Ltd'!D26/'Raw Data Trent Ltd'!D$17 -> 0.019644595 | F13: ='Raw Data Trent Ltd'!E26/'Raw Data Trent Ltd'!E$17 -> 0.070924102 | G13: ='Raw Data Trent Ltd'!F26/'Raw Data Trent Ltd'!F$17 -> 0.099230223 | H13: ='Raw Data Trent Ltd'!G26/'Raw Data Trent Ltd'!G$17 -> 0.069101516 | I13: ='Raw Data Trent Ltd'!H26/'Raw Data Trent Ltd'!H$17 -> 0.059899151 | J13: ='Raw Data Trent Ltd'!I26/'Raw Data Trent Ltd'!I$17 -> 0.054230629 | ... L13: ='Raw Data Trent Ltd'!K26/'Raw Data Trent Ltd'!K$17 -> 0.067807899
B14: ='Raw Data Trent Ltd'!A27 -> Interest | C14: ='Raw Data Trent Ltd'!B27/'Raw Data Trent Ltd'!B$17 -> 0.025131866 | D14: ='Raw Data Trent Ltd'!C27/'Raw Data Trent Ltd'!C$17 -> 0.020292381 | E14: ='Raw Data Trent Ltd'!D27/'Raw Data Trent Ltd'!D$17 -> 0.019252996 | F14: ='Raw Data Trent Ltd'!E27/'Raw Data Trent Ltd'!E$17 -> 0.075551208 | G14: ='Raw Data Trent Ltd'!F27/'Raw Data Trent Ltd'!F$17 -> 0.10057618 | H14: ='Raw Data Trent Ltd'!G27/'Raw Data Trent Ltd'!G$17 -> 0.072218443 | I14: ='Raw Data Trent Ltd'!H27/'Raw Data Trent Ltd'!H$17 -> 0.049622544 | J14: ='Raw Data Trent Ltd'!I27/'Raw Data Trent Ltd'!I$17 -> 0.029709635 | ... L14: ='Raw Data Trent Ltd'!K27/'Raw Data Trent Ltd'!K$17 -> 0.0083863823
B15: ='Raw Data Trent Ltd'!A28 -> Profit before tax | C15: ='Raw Data Trent Ltd'!B28/'Raw Data Trent Ltd'!B$17 -> 0.070623028 | D15: ='Raw Data Trent Ltd'!C28/'Raw Data Trent Ltd'!C$17 -> 0.067978085 | E15: ='Raw Data Trent Ltd'!D28/'Raw Data Trent Ltd'!D$17 -> 0.064051189 | F15: ='Raw Data Trent Ltd'!E28/'Raw Data Trent Ltd'!E$17 -> 0.047329589 | G15: ='Raw Data Trent Ltd'!F28/'Raw Data Trent Ltd'!F$17 -> -0.078990806 | H15: ='Raw Data Trent Ltd'!G28/'Raw Data Trent Ltd'!G$17 -> 0.024726435 | I15: ='Raw Data Trent Ltd'!H28/'Raw Data Trent Ltd'!H$17 -> 0.066982366 | J15: ='Raw Data Trent Ltd'!I28/'Raw Data Trent Ltd'!I$17 -> 0.15521721 | ... L15: ='Raw Data Trent Ltd'!K28/'Raw Data Trent Ltd'!K$17 -> 0.11141061
... B18: ='Raw Data Trent Ltd'!A31 -> Dividend Amount | C18: ='Raw Data Trent Ltd'!B31/'Raw Data Trent Ltd'!B$17 -> 0.0183344 | D18: ='Raw Data Trent Ltd'!C31/'Raw Data Trent Ltd'!C$17 -> 0.017710641 | E18: ='Raw Data Trent Ltd'!D31/'Raw Data Trent Ltd'!D$17 -> 0.016424357 | F18: ='Raw Data Trent Ltd'!E31/'Raw Data Trent Ltd'!E$17 -> 0.010197993 | G18: ='Raw Data Trent Ltd'!F31/'Raw Data Trent Ltd'!F$17 -> 0.00822612 | H18: ='Raw Data Trent Ltd'!G31/'Raw Data Trent Ltd'!G$17 -> 0.013437023 | I18: ='Raw Data Trent Ltd'!H31/'Raw Data Trent Ltd'!H$17 -> 0.0094891786 | J18: ='Raw Data Trent Ltd'!I31/'Raw Data Trent Ltd'!I$17 -> 0.0091926456 | ... L18: ='Raw Data Trent Ltd'!K31/'Raw Data Trent Ltd'!K$17 -> 0.010625574
B19: ='Raw Data Trent Ltd'!A34 -> EBITDA | C19: ='Raw Data Trent Ltd'!B34/'Raw Data Trent Ltd'!B$17 -> 0.11848668 | D19: ='Raw Data Trent Ltd'!C34/'Raw Data Trent Ltd'!C$17 -> 0.10934154 | E19: ='Raw Data Trent Ltd'!D34/'Raw Data Trent Ltd'!D$17 -> 0.10374719 | F19: ='Raw Data Trent Ltd'!E34/'Raw Data Trent Ltd'!E$17 -> 0.19864428 | G19: ='Raw Data Trent Ltd'!F34/'Raw Data Trent Ltd'!F$17 -> 0.13429825 | H19: ='Raw Data Trent Ltd'!G34/'Raw Data Trent Ltd'!G$17 -> 0.18188225 | I19: ='Raw Data Trent Ltd'!H34/'Raw Data Trent Ltd'!H$17 -> 0.18269186 | J19: ='Raw Data Trent Ltd'!I34/'Raw Data Trent Ltd'!I$17 -> 0.23991221 | ... L19: ='Raw Data Trent Ltd'!K34/'Raw Data Trent Ltd'!K$17 -> 0.1875212
B21: ="Common Size Balance Sheet"&" "&"-"&" "&'Raw Data Trent Ltd'!B1 -> Common Size Balance Sheet - TRENT LTD
B22: Particulars | C22: ='Raw Data Trent Ltd'!$B$16 -> 42825 | D22: =C22+365 -> 43190 | E22: =D22+365 -> 43555 | F22: =E22+365 -> 43920 | G22: =F22+365 -> 44285 | H22: =G22+365 -> 44650 | I22: =H22+365 -> 45015 | J22: =I22+365 -> 45380 | K22: =J22+365 -> 45745 | L22: =K22+365 -> 46110
B23: Total Liablities | C23: ='Raw Data Trent Ltd'!B61/'Raw Data Trent Ltd'!B$61 -> 1 | D23: ='Raw Data Trent Ltd'!C61/'Raw Data Trent Ltd'!C$61 -> 1 | E23: ='Raw Data Trent Ltd'!D61/'Raw Data Trent Ltd'!D$61 -> 1 | F23: ='Raw Data Trent Ltd'!E61/'Raw Data Trent Ltd'!E$61 -> 1 | G23: ='Raw Data Trent Ltd'!F61/'Raw Data Trent Ltd'!F$61 -> 1 | H23: ='Raw Data Trent Ltd'!G61/'Raw Data Trent Ltd'!G$61 -> 1 | I23: ='Raw Data Trent Ltd'!H61/'Raw Data Trent Ltd'!H$61 -> 1 | J23: ='Raw Data Trent Ltd'!I61/'Raw Data Trent Ltd'!I$61 -> 1 | ... L23: ='Raw Data Trent Ltd'!K61/'Raw Data Trent Ltd'!K$61 -> 1
B24: ='Raw Data Trent Ltd'!A57 -> Equity Share Capital | C24: ='Raw Data Trent Ltd'!B57/'Raw Data Trent Ltd'!B$61 -> 0.014953313 | D24: ='Raw Data Trent Ltd'!C57/'Raw Data Trent Ltd'!C$61 -> 0.014226024 | E24: ='Raw Data Trent Ltd'!D57/'Raw Data Trent Ltd'!D$61 -> 0.012986759 | F24: ='Raw Data Trent Ltd'!E57/'Raw Data Trent Ltd'!E$61 -> 0.0064557955 | G24: ='Raw Data Trent Ltd'!F57/'Raw Data Trent Ltd'!F$61 -> 0.0062109848 | H24: ='Raw Data Trent Ltd'!G57/'Raw Data Trent Ltd'!G$61 -> 0.0046013342 | I24: ='Raw Data Trent Ltd'!H57/'Raw Data Trent Ltd'!H$61 -> 0.0043989195 | J24: ='Raw Data Trent Ltd'!I57/'Raw Data Trent Ltd'!I$61 -> 0.0049638706 | ... L24: ='Raw Data Trent Ltd'!K57/'Raw Data Trent Ltd'!K$61 -> 0.0030310575
B25: ='Raw Data Trent Ltd'!A58 -> Reserves | C25: ='Raw Data Trent Ltd'!B58/'Raw Data Trent Ltd'!B$61 -> 0.68149848 | D25: ='Raw Data Trent Ltd'!C58/'Raw Data Trent Ltd'!C$61 -> 0.6687644 | E25: ='Raw Data Trent Ltd'!D58/'Raw Data Trent Ltd'!D$61 -> 0.63049289 | F25: ='Raw Data Trent Ltd'!E58/'Raw Data Trent Ltd'!E$61 -> 0.42715756 | G25: ='Raw Data Trent Ltd'!F58/'Raw Data Trent Ltd'!F$61 -> 0.39790137 | H25: ='Raw Data Trent Ltd'!G58/'Raw Data Trent Ltd'!G$61 -> 0.30137768 | I25: ='Raw Data Trent Ltd'!H58/'Raw Data Trent Ltd'!H$61 -> 0.31676428 | J25: ='Raw Data Trent Ltd'!I58/'Raw Data Trent Ltd'!I$61 -> 0.56301742 | ... L25: ='Raw Data Trent Ltd'!K58/'Raw Data Trent Ltd'!K$61 -> 0.59249543
B26: ='Raw Data Trent Ltd'!A59 -> Borrowings | C26: ='Raw Data Trent Ltd'!B59/'Raw Data Trent Ltd'!B$61 -> 0.1762808 | D26: ='Raw Data Trent Ltd'!C59/'Raw Data Trent Ltd'!C$61 -> 0.16757426 | E26: ='Raw Data Trent Ltd'!D59/'Raw Data Trent Ltd'!D$61 -> 0.19311698 | F26: ='Raw Data Trent Ltd'!E59/'Raw Data Trent Ltd'!E$61 -> 0.054432072 | G26: ='Raw Data Trent Ltd'!F59/'Raw Data Trent Ltd'!F$61 -> 0.51777949 | H26: ='Raw Data Trent Ltd'!G59/'Raw Data Trent Ltd'!G$61 -> 0.61161633 | I26: ='Raw Data Trent Ltd'!H59/'Raw Data Trent Ltd'!H$61 -> 0.55238798 | J26: ='Raw Data Trent Ltd'!I59/'Raw Data Trent Ltd'!I$61 -> 0.24477118 | ... L26: ='Raw Data Trent Ltd'!K59/'Raw Data Trent Ltd'!K$61 -> 0.21837682
B27: ='Raw Data Trent Ltd'!A60 -> Other Liabilities | C27: ='Raw Data Trent Ltd'!B60/'Raw Data Trent Ltd'!B$61 -> 0.12726741 | D27: ='Raw Data Trent Ltd'!C60/'Raw Data Trent Ltd'!C$61 -> 0.14943533 | E27: ='Raw Data Trent Ltd'!D60/'Raw Data Trent Ltd'!D$61 -> 0.16340337 | F27: ='Raw Data Trent Ltd'!E60/'Raw Data Trent Ltd'!E$61 -> 0.51195457 | G27: ='Raw Data Trent Ltd'!F60/'Raw Data Trent Ltd'!F$61 -> 0.078108157 | H27: ='Raw Data Trent Ltd'!G60/'Raw Data Trent Ltd'!G$61 -> 0.082404653 | I27: ='Raw Data Trent Ltd'!H60/'Raw Data Trent Ltd'!H$61 -> 0.12644883 | J27: ='Raw Data Trent Ltd'!I60/'Raw Data Trent Ltd'!I$61 -> 0.18724753 | ... L27: ='Raw Data Trent Ltd'!K60/'Raw Data Trent Ltd'!K$61 -> 0.1860967
B29: Total Assets | C29: ='Raw Data Trent Ltd'!B77/'Raw Data Trent Ltd'!B$77 -> 1 | D29: ='Raw Data Trent Ltd'!C77/'Raw Data Trent Ltd'!C$77 -> 1 | E29: ='Raw Data Trent Ltd'!D77/'Raw Data Trent Ltd'!D$77 -> 1 | F29: ='Raw Data Trent Ltd'!E77/'Raw Data Trent Ltd'!E$77 -> 1 | G29: ='Raw Data Trent Ltd'!F77/'Raw Data Trent Ltd'!F$77 -> 1 | H29: ='Raw Data Trent Ltd'!G77/'Raw Data Trent Ltd'!G$77 -> 1 | I29: ='Raw Data Trent Ltd'!H77/'Raw Data Trent Ltd'!H$77 -> 1 | J29: ='Raw Data Trent Ltd'!I77/'Raw Data Trent Ltd'!I$77 -> 1 | ... L29: ='Raw Data Trent Ltd'!K77/'Raw Data Trent Ltd'!K$77 -> 1
B30: ='Raw Data Trent Ltd'!A62 -> Net Block | C30: ='Raw Data Trent Ltd'!B62/'Raw Data Trent Ltd'!B$77 -> 0.24691641 | D30: ='Raw Data Trent Ltd'!C62/'Raw Data Trent Ltd'!C$77 -> 0.2622289 | E30: ='Raw Data Trent Ltd'!D62/'Raw Data Trent Ltd'!D$77 -> 0.25878941 | F30: ='Raw Data Trent Ltd'!E62/'Raw Data Trent Ltd'!E$77 -> 0.49729238 | G30: ='Raw Data Trent Ltd'!F62/'Raw Data Trent Ltd'!F$77 -> 0.5335367 | H30: ='Raw Data Trent Ltd'!G62/'Raw Data Trent Ltd'!G$77 -> 0.60661375 | I30: ='Raw Data Trent Ltd'!H62/'Raw Data Trent Ltd'!H$77 -> 0.56016002 | J30: ='Raw Data Trent Ltd'!I62/'Raw Data Trent Ltd'!I$77 -> 0.34208399 | ... L30: ='Raw Data Trent Ltd'!K62/'Raw Data Trent Ltd'!K$77 -> 0.47053778
B31: ='Raw Data Trent Ltd'!A63 -> Capital Work in Progress | C31: ='Raw Data Trent Ltd'!B63/'Raw Data Trent Ltd'!B$77 -> 0.0024659692 | D31: ='Raw Data Trent Ltd'!C63/'Raw Data Trent Ltd'!C$77 -> 0.0041055543 | E31: ='Raw Data Trent Ltd'!D63/'Raw Data Trent Ltd'!D$77 -> 0.034071191 | F31: ='Raw Data Trent Ltd'!E63/'Raw Data Trent Ltd'!E$77 -> 0.0042348566 | G31: ='Raw Data Trent Ltd'!F63/'Raw Data Trent Ltd'!F$77 -> 0.01886532 | H31: ='Raw Data Trent Ltd'!G63/'Raw Data Trent Ltd'!G$77 -> 0.013554197 | I31: ='Raw Data Trent Ltd'!H63/'Raw Data Trent Ltd'!H$77 -> 0.012586726 | J31: ='Raw Data Trent Ltd'!I63/'Raw Data Trent Ltd'!I$77 -> 0.031246553 | ... L31: ='Raw Data Trent Ltd'!K63/'Raw Data Trent Ltd'!K$77 -> 0.021655648
B32: ='Raw Data Trent Ltd'!A64 -> Investments | C32: ='Raw Data Trent Ltd'!B64/'Raw Data Trent Ltd'!B$77 -> 0.48597593 | D32: ='Raw Data Trent Ltd'!C64/'Raw Data Trent Ltd'!C$77 -> 0.43790296 | E32: ='Raw Data Trent Ltd'!D64/'Raw Data Trent Ltd'!D$77 -> 0.34502259 | F32: ='Raw Data Trent Ltd'!E64/'Raw Data Trent Ltd'!E$77 -> 0.27508045 | G32: ='Raw Data Trent Ltd'!F64/'Raw Data Trent Ltd'!F$77 -> 0.25984629 | H32: ='Raw Data Trent Ltd'!G64/'Raw Data Trent Ltd'!G$77 -> 0.16615541 | I32: ='Raw Data Trent Ltd'!H64/'Raw Data Trent Ltd'!H$77 -> 0.13733414 | J32: ='Raw Data Trent Ltd'!I64/'Raw Data Trent Ltd'!I$77 -> 0.19772123 | ... L32: ='Raw Data Trent Ltd'!K64/'Raw Data Trent Ltd'!K$77 -> 0.11807994
B33: ='Raw Data Trent Ltd'!A65 -> Other Assets | C33: ='Raw Data Trent Ltd'!B75/'Raw Data Trent Ltd'!B$77 -> 0.10914164 | D33: ='Raw Data Trent Ltd'!C75/'Raw Data Trent Ltd'!C$77 -> 0.1276532 | E33: ='Raw Data Trent Ltd'!D75/'Raw Data Trent Ltd'!D$77 -> 0.14022026 | F33: ='Raw Data Trent Ltd'!E75/'Raw Data Trent Ltd'!E$77 -> 0.098754603 | G33: ='Raw Data Trent Ltd'!F75/'Raw Data Trent Ltd'!F$77 -> 0.095044665 | H33: ='Raw Data Trent Ltd'!G75/'Raw Data Trent Ltd'!G$77 -> 0.087866715 | I33: ='Raw Data Trent Ltd'!H75/'Raw Data Trent Ltd'!H$77 -> 0.10655656 | J33: ='Raw Data Trent Ltd'!I75/'Raw Data Trent Ltd'!I$77 -> 0.15498866 | ... L33: ='Raw Data Trent Ltd'!K75/'Raw Data Trent Ltd'!K$77 -> 0.16607211
B34: ='Raw Data Trent Ltd'!A67 -> Receivables | C34: ='Raw Data Trent Ltd'!B67/'Raw Data Trent Ltd'!B$77 -> 0.0026639667 | D34: ='Raw Data Trent Ltd'!C67/'Raw Data Trent Ltd'!C$77 -> 0.0064644285 | E34: ='Raw Data Trent Ltd'!D67/'Raw Data Trent Ltd'!D$77 -> 0.0064640685 | F34: ='Raw Data Trent Ltd'!E67/'Raw Data Trent Ltd'!E$77 -> 0.0031089513 | G34: ='Raw Data Trent Ltd'!F67/'Raw Data Trent Ltd'!F$77 -> 0.0036287526 | H34: ='Raw Data Trent Ltd'!G67/'Raw Data Trent Ltd'!G$77 -> 0.002363442 | I34: ='Raw Data Trent Ltd'!H67/'Raw Data Trent Ltd'!H$77 -> 0.0042553823 | J34: ='Raw Data Trent Ltd'!I67/'Raw Data Trent Ltd'!I$77 -> 0.011413412 | ... L34: ='Raw Data Trent Ltd'!K67/'Raw Data Trent Ltd'!K$77 -> 0.0043602891
B35: ='Raw Data Trent Ltd'!A68 -> Inventory | C35: ='Raw Data Trent Ltd'!B68/'Raw Data Trent Ltd'!B$77 -> 0.13741028 | D35: ='Raw Data Trent Ltd'!C68/'Raw Data Trent Ltd'!C$77 -> 0.14759874 | E35: ='Raw Data Trent Ltd'!D68/'Raw Data Trent Ltd'!D$77 -> 0.19423862 | F35: ='Raw Data Trent Ltd'!E68/'Raw Data Trent Ltd'!E$77 -> 0.11037685 | G35: ='Raw Data Trent Ltd'!F68/'Raw Data Trent Ltd'!F$77 -> 0.074844551 | H35: ='Raw Data Trent Ltd'!G68/'Raw Data Trent Ltd'!G$77 -> 0.11231915 | I35: ='Raw Data Trent Ltd'!H68/'Raw Data Trent Ltd'!H$77 -> 0.1684285 | J35: ='Raw Data Trent Ltd'!I68/'Raw Data Trent Ltd'!I$77 -> 0.22099766 | ... L35: ='Raw Data Trent Ltd'!K68/'Raw Data Trent Ltd'!K$77 -> 0.19516514
B36: ='Raw Data Trent Ltd'!A69 -> Cash & Bank | C36: ='Raw Data Trent Ltd'!B69/'Raw Data Trent Ltd'!B$77 -> 0.015425807 | D36: ='Raw Data Trent Ltd'!C69/'Raw Data Trent Ltd'!C$77 -> 0.014046219 | E36: ='Raw Data Trent Ltd'!D69/'Raw Data Trent Ltd'!D$77 -> 0.02119386 | F36: ='Raw Data Trent Ltd'!E69/'Raw Data Trent Ltd'!E$77 -> 0.01115191 | G36: ='Raw Data Trent Ltd'!F69/'Raw Data Trent Ltd'!F$77 -> 0.014233725 | H36: ='Raw Data Trent Ltd'!G69/'Raw Data Trent Ltd'!G$77 -> 0.011127333 | I36: ='Raw Data Trent Ltd'!H69/'Raw Data Trent Ltd'!H$77 -> 0.010678671 | J36: ='Raw Data Trent Ltd'!I69/'Raw Data Trent Ltd'!I$77 -> 0.041548504 | ... L36: ='Raw Data Trent Ltd'!K69/'Raw Data Trent Ltd'!K$77 -> 0.024129093

Sheet Ratio Analysis Trent Ltd
B2: ="Ratio Analysis of - "&'Raw Data Trent Ltd'!B1 -> Ratio Analysis of - TRENT LTD
B3: Years | C3: ='Raw Data Trent Ltd'!B16 -> 42825 | D3: =C3+365 -> 43190 | E3: =D3+365 -> 43555 | F3: =E3+365 -> 43920 | G3: =F3+365 -> 44285 | H3: =G3+365 -> 44650 | I3: =H3+365 -> 45015 | J3: =I3+365 -> 45380 | K3: =J3+365 -> 45745 | L3: =K3+365 -> 46110 | M3: Trend | N3: Mean | O3: Median
B5: SalesGrowth | D5: =IFERROR('Historical IFS Trent Ltd'!D7,0) -> 0.19036216 | E5: =IFERROR('Historical IFS Trent Ltd'!E7,0) -> 0.21913732 | F5: =IFERROR('Historical IFS Trent Ltd'!F7,0) -> 0.32534674 | G5: =IFERROR('Historical IFS Trent Ltd'!G7,0) -> -0.25617473 | H5: =IFERROR('Historical IFS Trent Ltd'!H7,0) -> 0.73470474 | I5: =IFERROR('Historical IFS Trent Ltd'!I7,0) -> 0.83236624 | J5: =IFERROR('Historical IFS Trent Ltd'!J7,0) -> 0.50146566 | K5: =IFERROR('Historical IFS Trent Ltd'!K7,0) -> 0.38460264 | L5: =IFERROR('Historical IFS Trent Ltd'!L7,0) -> 0.1715592 | N5: =IFERROR(AVERAGE(D5:L5),0) -> 0.34481889 | O5: =IFERROR(MEDIAN(D5:L5),0) -> 0.32534674
B6: EBITDA Growth | D6: =IFERROR(('Historical IFS Trent Ltd'!D18/'Historical IFS Trent Ltd'!C18)-1,0) -> 0.56144687 | E6: =IFERROR(('Historical IFS Trent Ltd'!E18/'Historical IFS Trent Ltd'!D18)-1,0) -> 0.15414868 | F6: =IFERROR(('Historical IFS Trent Ltd'!F18/'Historical IFS Trent Ltd'!E18)-1,0) -> 1.1981799 | G6: =IFERROR(('Historical IFS Trent Ltd'!G18/'Historical IFS Trent Ltd'!F18)-1,0) -> -0.78473259 | H6: =IFERROR(('Historical IFS Trent Ltd'!H18/'Historical IFS Trent Ltd'!G18)-1,0) -> 4.2227979 | I6: =IFERROR(('Historical IFS Trent Ltd'!I18/'Historical IFS Trent Ltd'!H18)-1,0) -> 0.87340261 | J6: =IFERROR(('Historical IFS Trent Ltd'!J18/'Historical IFS Trent Ltd'!I18)-1,0) -> 0.76878338 | K6: =IFERROR(('Historical IFS Trent Ltd'!K18/'Historical IFS Trent Ltd'!J18)-1,0) -> 0.43095058 | L6: =IFERROR(('Historical IFS Trent Ltd'!L18/'Historical IFS Trent Ltd'!K18)-1,0) -> 0.30263904 | N6: =IFERROR(AVERAGE(D6:L6),0) -> 0.85862404 | O6: =IFERROR(MEDIAN(D6:L6),0) -> 0.56144687
B7: EBIT Growth | D7: =IFERROR(('Historical IFS Trent Ltd'!D27/'Historical IFS Trent Ltd'!C27)-1,0) -> 1.552795 | E7: =IFERROR(('Historical IFS Trent Ltd'!E27/'Historical IFS Trent Ltd'!D27)-1,0) -> 0.16058394 | F7: =IFERROR(('Historical IFS Trent Ltd'!F27/'Historical IFS Trent Ltd'!E27)-1,0) -> -0.86727391 | G7: =IFERROR(('Historical IFS Trent Ltd'!G27/'Historical IFS Trent Ltd'!F27)-1,0) -> -23.01634 | H7: =IFERROR(('Historical IFS Trent Ltd'!H27/'Historical IFS Trent Ltd'!G27)-1,0) -> -0.89871852 | I7: =IFERROR(('Historical IFS Trent Ltd'!I27/'Historical IFS Trent Ltd'!H27)-1,0) -> -6.1653639 | J7: =IFERROR(('Historical IFS Trent Ltd'!J27/'Historical IFS Trent Ltd'!I27)-1,0) -> 3.4068662 | K7: =IFERROR(('Historical IFS Trent Ltd'!K27/'Historical IFS Trent Ltd'!J27)-1,0) -> 0.85067388 | L7: =IFERROR(('Historical IFS Trent Ltd'!L27/'Historical IFS Trent Ltd'!K27)-1,0) -> 0.24304219 | N7: =IFERROR(AVERAGE(D7:L7),0) -> -2.7481928 | O7: =IFERROR(MEDIAN(D7:L7),0) -> 0.16058394
B8: Net Profit Growth | D8: =IFERROR(('Historical IFS Trent Ltd'!D33/'Historical IFS Trent Ltd'!C33)-1,0) -> 15.365385 | E8: =IFERROR(('Historical IFS Trent Ltd'!E33/'Historical IFS Trent Ltd'!D33)-1,0) -> 0.086452913 | F8: =IFERROR(('Historical IFS Trent Ltd'!F33/'Historical IFS Trent Ltd'!E33)-1,0) -> -1.6280902 | G8: =IFERROR(('Historical IFS Trent Ltd'!G33/'Historical IFS Trent Ltd'!F33)-1,0) -> 8.3611316 | H8: =IFERROR(('Historical IFS Trent Ltd'!H33/'Historical IFS Trent Ltd'!G33)-1,0) -> -0.69106247 | I8: =IFERROR(('Historical IFS Trent Ltd'!I33/'Historical IFS Trent Ltd'!H33)-1,0) -> -1.4510888 | J8: =IFERROR(('Historical IFS Trent Ltd'!J33/'Historical IFS Trent Ltd'!I33)-1,0) -> 8.2127098 | K8: =IFERROR(('Historical IFS Trent Ltd'!K33/'Historical IFS Trent Ltd'!J33)-1,0) -> 1.5163238 | L8: =IFERROR(('Historical IFS Trent Ltd'!L33/'Historical IFS Trent Ltd'!K33)-1,0) -> 0.32484646 | N8: =IFERROR(AVERAGE(D8:L8),0) -> 3.3440675 | O8: =IFERROR(MEDIAN(D8:L8),0) -> 0.32484646
B9: Dividend Growth | D9: =IFERROR(('Historical IFS Trent Ltd'!D41/'Historical IFS Trent Ltd'!C41)-1,0) -> 0.14986458 | E9: =IFERROR(('Historical IFS Trent Ltd'!E41/'Historical IFS Trent Ltd'!D41)-1,0) -> 0.13059409 | F9: =IFERROR(('Historical IFS Trent Ltd'!F41/'Historical IFS Trent Ltd'!E41)-1,0) -> -0.23078704 | G9: =IFERROR(('Historical IFS Trent Ltd'!G41/'Historical IFS Trent Ltd'!F41)-1,0) -> -0.4 | H9: =IFERROR(('Historical IFS Trent Ltd'!H41/'Historical IFS Trent Ltd'!G41)-1,0) -> 1.8335677 | I9: =IFERROR(('Historical IFS Trent Ltd'!I41/'Historical IFS Trent Ltd'!H41)-1,0) -> 0.29401059 | J9: =IFERROR(('Historical IFS Trent Ltd'!J41/'Historical IFS Trent Ltd'!I41)-1,0) -> 0.45454545 | K9: =IFERROR(('Historical IFS Trent Ltd'!K41/'Historical IFS Trent Ltd'!J41)-1,0) -> 0.5625 | L9: =IFERROR(('Historical IFS Trent Ltd'!L41/'Historical IFS Trent Ltd'!K41)-1,0) -> 0.2 | N9: =IFERROR(AVERAGE(D9:L9),0) -> 0.33269949 | O9: =IFERROR(MEDIAN(D9:L9),0) -> 0.2
B11: Gross Margin | C11: =IFERROR('Historical IFS Trent Ltd'!C13,0) -> 0.33279446 | D11: =IFERROR('Historical IFS Trent Ltd'!D13,0) -> 0.34735291 | E11: =IFERROR('Historical IFS Trent Ltd'!E13,0) -> 0.32264736 | F11: =IFERROR('Historical IFS Trent Ltd'!F13,0) -> 0.30954567 | G11: =IFERROR('Historical IFS Trent Ltd'!G13,0) -> 0.23685286 | H11: =IFERROR('Historical IFS Trent Ltd'!H13,0) -> 0.31447837 | I11: =IFERROR('Historical IFS Trent Ltd'!I13,0) -> 0.30416573 | J11: =IFERROR('Historical IFS Trent Ltd'!J13,0) -> 0.31359156 | ... L11: =IFERROR('Historical IFS Trent Ltd'!L13,0) -> 0.37132271 | N11: =IFERROR(AVERAGE(C11:L11),0) -> 0.31685026 | O11: =IFERROR(AVERAGE(D11:M11),0) -> 0.31507868
B12: EBITDA Margin | C12: =IFERROR('Historical IFS Trent Ltd'!C19,0) -> 0.073674163 | D12: =IFERROR('Historical IFS Trent Ltd'!D19,0) -> 0.096641421 | E12: =IFERROR('Historical IFS Trent Ltd'!E19,0) -> 0.09148975 | F12: =IFERROR('Historical IFS Trent Ltd'!F19,0) -> 0.15174212 | G12: =IFERROR('Historical IFS Trent Ltd'!G19,0) -> 0.043915062 | H12: =IFERROR('Historical IFS Trent Ltd'!H19,0) -> 0.13221818 | I12: =IFERROR('Historical IFS Trent Ltd'!I19,0) -> 0.13517924 | J12: =IFERROR('Historical IFS Trent Ltd'!J19,0) -> 0.15924626 | ... L12: =IFERROR('Historical IFS Trent Ltd'!L19,0) -> 0.18299051 | N12: =IFERROR(AVERAGE(C12:L12),0) -> 0.12316736 | O12: =IFERROR(AVERAGE(D12:M12),0) -> 0.1286666
B13: EBIT Margin | C13: =IFERROR(('Historical IFS Trent Ltd'!C27+'Historical IFS Trent Ltd'!C21)/'Historical IFS Trent Ltd'!C6,0) -> 0.050892719 | D13: =IFERROR(('Historical IFS Trent Ltd'!D27+'Historical IFS Trent Ltd'!D21)/'Historical IFS Trent Ltd'!D6,0) -> 0.075537901 | E13: =IFERROR(('Historical IFS Trent Ltd'!E27+'Historical IFS Trent Ltd'!E21)/'Historical IFS Trent Ltd'!E6,0) -> 0.071845155 | F13: =IFERROR(('Historical IFS Trent Ltd'!F27+'Historical IFS Trent Ltd'!F21)/'Historical IFS Trent Ltd'!F6,0) -> 0.08081802 | G13: =IFERROR(('Historical IFS Trent Ltd'!G27+'Historical IFS Trent Ltd'!G21)/'Historical IFS Trent Ltd'!G6,0) -> -0.055315161 | H13: =IFERROR(('Historical IFS Trent Ltd'!H27+'Historical IFS Trent Ltd'!H21)/'Historical IFS Trent Ltd'!H6,0) -> 0.06311666 | I13: =IFERROR(('Historical IFS Trent Ltd'!I27+'Historical IFS Trent Ltd'!I21)/'Historical IFS Trent Ltd'!I6,0) -> 0.075280089 | J13: =IFERROR(('Historical IFS Trent Ltd'!J27+'Historical IFS Trent Ltd'!J21)/'Historical IFS Trent Ltd'!J6,0) -> 0.10501563 | ... L13: =IFERROR(('Historical IFS Trent Ltd'!L27+'Historical IFS Trent Ltd'!L21)/'Historical IFS Trent Ltd'!L6,0) -> 0.11518261 | N13: =IFERROR(AVERAGE(C13:L13),0) -> 0.06947065 | O13: =IFERROR(AVERAGE(D13:M13),0) -> 0.071534865
B14: EBT Margin | C14: =IFERROR('Historical IFS Trent Ltd'!C28,0) -> 0.025760853 | D14: =IFERROR('Historical IFS Trent Ltd'!D28,0) -> 0.05524552 | E14: =IFERROR('Historical IFS Trent Ltd'!E28,0) -> 0.052592159 | F14: =IFERROR('Historical IFS Trent Ltd'!F28,0) -> 0.0052668116 | G14: =IFERROR('Historical IFS Trent Ltd'!G28,0) -> -0.15589134 | H14: =IFERROR('Historical IFS Trent Ltd'!H28,0) -> -0.0091017826 | I14: =IFERROR('Historical IFS Trent Ltd'!I28,0) -> 0.025657545 | J14: =IFERROR('Historical IFS Trent Ltd'!J28,0) -> 0.075305997 | ... L14: =IFERROR('Historical IFS Trent Ltd'!L28,0) -> 0.10679623 | N14: =IFERROR(AVERAGE(C14:L14),0) -> 0.028228676 | O14: =IFERROR(AVERAGE(D14:M14),0) -> 0.028502878
B15: Net Profit Margin | C15: =IFERROR('Historical IFS Trent Ltd'!C34,0) -> 0.0020083423 | D15: =IFERROR('Historical IFS Trent Ltd'!D34,0) -> 0.027611172 | E15: =IFERROR('Historical IFS Trent Ltd'!E34,0) -> 0.02460612 | F15: =IFERROR('Historical IFS Trent Ltd'!F34,0) -> -0.011660996 | G15: =IFERROR('Historical IFS Trent Ltd'!G34,0) -> -0.14675506 | H15: =IFERROR('Historical IFS Trent Ltd'!H34,0) -> -0.026135944 | I15: =IFERROR('Historical IFS Trent Ltd'!I34,0) -> 0.0064341023 | J15: =IFERROR('Historical IFS Trent Ltd'!J34,0) -> 0.039478437 | ... L15: =IFERROR('Historical IFS Trent Ltd'!L34,0) -> 0.081133952 | N15: =IFERROR(AVERAGE(C15:L15),0) -> 0.0068466725 | O15: =IFERROR(AVERAGE(D15:M15),0) -> 0.0073842647
B17: SalesExpenses%Sales | C17: =IFERROR('Historical IFS Trent Ltd'!C16,0) -> 0.2591203 | D17: =IFERROR('Historical IFS Trent Ltd'!D16,0) -> 0.25071148 | E17: =IFERROR('Historical IFS Trent Ltd'!E16,0) -> 0.23115761 | F17: =IFERROR('Historical IFS Trent Ltd'!F16,0) -> 0.15780354 | G17: =IFERROR('Historical IFS Trent Ltd'!G16,0) -> 0.1929378 | H17: =IFERROR('Historical IFS Trent Ltd'!H16,0) -> 0.18226019 | I17: =IFERROR('Historical IFS Trent Ltd'!I16,0) -> 0.16898649 | J17: =IFERROR('Historical IFS Trent Ltd'!J16,0) -> 0.15434529 | ... L17: =IFERROR('Historical IFS Trent Ltd'!L16,0) -> 0.18833219 | N17: =IFERROR(AVERAGE(C17:L17),0) -> 0.19368291 | O17: =IFERROR(AVERAGE(D17:M17),0) -> 0.18641208
B18: Depreciation%Sales | C18: =IFERROR('Historical IFS Trent Ltd'!C25,0) -> 0.022781444 | D18: =IFERROR('Historical IFS Trent Ltd'!D25,0) -> 0.02110352 | E18: =IFERROR('Historical IFS Trent Ltd'!E25,0) -> 0.019644595 | F18: =IFERROR('Historical IFS Trent Ltd'!F25,0) -> 0.070924102 | G18: =IFERROR('Historical IFS Trent Ltd'!G25,0) -> 0.099230223 | H18: =IFERROR('Historical IFS Trent Ltd'!H25,0) -> 0.069101516 | I18: =IFERROR('Historical IFS Trent Ltd'!I25,0) -> 0.059899151 | J18: =IFERROR('Historical IFS Trent Ltd'!J25,0) -> 0.054230629 | ... L18: =IFERROR('Historical IFS Trent Ltd'!L25,0) -> 0.067807899 | N18: =IFERROR(AVERAGE(C18:L18),0) -> 0.053696705 | O18: =IFERROR(AVERAGE(D18:M18),0) -> 0.057131734
B19: OperatingIncome%Sales | C19: =C13 -> 0.050892719 | D19: =D13 -> 0.075537901 | E19: =E13 -> 0.071845155 | F19: =F13 -> 0.08081802 | G19: =G13 -> -0.055315161 | H19: =H13 -> 0.06311666 | I19: =I13 -> 0.075280089 | J19: =J13 -> 0.10501563 | ... L19: =L13 -> 0.11518261 | N19: =IFERROR(AVERAGE(C19:L19),0) -> 0.06947065 | O19: =IFERROR(AVERAGE(D19:M19),0) -> 0.071534865
B21: Return on Capital Employed | C21: =IFERROR(('Historical IFS Trent Ltd'!C27+'Historical IFS Trent Ltd'!C21)/SUM('Historical IFS Trent Ltd'!C47:C49),0) -> 0.047560366 | D21: =IFERROR(('Historical IFS Trent Ltd'!D27+'Historical IFS Trent Ltd'!D21)/SUM('Historical IFS Trent Ltd'!D47:D49),0) -> 0.082026374 | E21: =IFERROR(('Historical IFS Trent Ltd'!E27+'Historical IFS Trent Ltd'!E21)/SUM('Historical IFS Trent Ltd'!E47:E49),0) -> 0.088276925 | F21: =IFERROR(('Historical IFS Trent Ltd'!F27+'Historical IFS Trent Ltd'!F21)/SUM('Historical IFS Trent Ltd'!F47:F49),0) -> 0.10482938 | G21: =IFERROR(('Historical IFS Trent Ltd'!G27+'Historical IFS Trent Ltd'!G21)/SUM('Historical IFS Trent Ltd'!G47:G49),0) -> -0.027181967 | H21: =IFERROR(('Historical IFS Trent Ltd'!H27+'Historical IFS Trent Ltd'!H21)/SUM('Historical IFS Trent Ltd'!H47:H49),0) -> 0.040045928 | I21: =IFERROR(('Historical IFS Trent Ltd'!I27+'Historical IFS Trent Ltd'!I21)/SUM('Historical IFS Trent Ltd'!I47:I49),0) -> 0.087888459 | J21: =IFERROR(('Historical IFS Trent Ltd'!J27+'Historical IFS Trent Ltd'!J21)/SUM('Historical IFS Trent Ltd'!J47:J49),0) -> 0.22326753 | ... L21: =IFERROR(('Historical IFS Trent Ltd'!L27+'Historical IFS Trent Ltd'!L21)/SUM('Historical IFS Trent Ltd'!L47:L49),0) -> 0.24221841 | N21: =IFERROR(AVERAGE(C21:L21),0) -> 0.11389376 | O21: =IFERROR(AVERAGE(D21:M21),0) -> 0.12126413
B22: Retained Earnings% | C22: =IFERROR('Historical IFS Trent Ltd'!C44,0) -> 0 | D22: =IFERROR('Historical IFS Trent Ltd'!D44,0) -> 0.35856975 | E22: =IFERROR('Historical IFS Trent Ltd'!E44,0) -> 0.33250927 | F22: =IFERROR('Historical IFS Trent Ltd'!F44,0) -> 0 | G22: =IFERROR('Historical IFS Trent Ltd'!G44,0) -> 0 | H22: =IFERROR('Historical IFS Trent Ltd'!H44,0) -> 0 | I22: =IFERROR('Historical IFS Trent Ltd'!I44,0) -> 0 | J22: =IFERROR('Historical IFS Trent Ltd'!J44,0) -> 0.76714768 | ... L22: =IFERROR('Historical IFS Trent Ltd'!L44,0) -> 0.86903666 | N22: =IFERROR(AVERAGE(C22:L22),0) -> 0.31826748 | O22: =IFERROR(AVERAGE(D22:M22),0) -> 0.35363053
B23: Return on Equity% | C23: =IFERROR('Historical IFS Trent Ltd'!C33/SUM('Historical IFS Trent Ltd'!C47:C48),0) -> 0.0023518922 | D23: =IFERROR('Historical IFS Trent Ltd'!D33/SUM('Historical IFS Trent Ltd'!D47:D48),0) -> 0.037339301 | E23: =IFERROR('Historical IFS Trent Ltd'!E33/SUM('Historical IFS Trent Ltd'!E47:E48),0) -> 0.039307383 | F23: =IFERROR('Historical IFS Trent Ltd'!F33/SUM('Historical IFS Trent Ltd'!F47:F48),0) -> -0.017024253 | G23: =IFERROR('Historical IFS Trent Ltd'!G33/SUM('Historical IFS Trent Ltd'!G47:G48),0) -> -0.16451581 | H23: =IFERROR('Historical IFS Trent Ltd'!H33/SUM('Historical IFS Trent Ltd'!H47:H48),0) -> -0.049729272 | I23: =IFERROR('Historical IFS Trent Ltd'!I33/SUM('Historical IFS Trent Ltd'!I47:I48),0) -> 0.020431595 | J23: =IFERROR('Historical IFS Trent Ltd'!J33/SUM('Historical IFS Trent Ltd'!J47:J48),0) -> 0.12010355 | ... L23: =IFERROR('Historical IFS Trent Ltd'!L33/SUM('Historical IFS Trent Ltd'!L47:L48),0) -> 0.23318176 | N23: =IFERROR(AVERAGE(C23:L23),0) -> 0.04465301 | O23: =IFERROR(AVERAGE(D23:M23),0) -> 0.049353134
B24: Self Sustained Growth Rate | C24: =IFERROR(C22*C23,0) -> 0 | D24: =IFERROR(D22*D23,0) -> 0.013388744 | E24: =IFERROR(E22*E23,0) -> 0.013070069 | F24: =IFERROR(F22*F23,0) -> 0 | G24: =IFERROR(G22*G23,0) -> 0 | H24: =IFERROR(H22*H23,0) -> 0 | I24: =IFERROR(I22*I23,0) -> 0 | J24: =IFERROR(J22*J23,0) -> 0.092137157 | ... L24: =IFERROR(L22*L23,0) -> 0.2026435 | N24: =IFERROR(AVERAGE(C24:L24),0) -> 0.051377884 | O24: =IFERROR(AVERAGE(D24:M24),0) -> 0.057086538
B25: Interest Coverage Ratio | C25: =IFERROR(('Historical IFS Trent Ltd'!C27+'Historical IFS Trent Ltd'!C21)/'Historical IFS Trent Ltd'!C21,0) -> 2.0250274 | D25: =IFERROR(('Historical IFS Trent Ltd'!D27+'Historical IFS Trent Ltd'!D21)/'Historical IFS Trent Ltd'!D21,0) -> 3.722476 | E25: =IFERROR(('Historical IFS Trent Ltd'!E27+'Historical IFS Trent Ltd'!E21)/'Historical IFS Trent Ltd'!E21,0) -> 3.7316351 | F25: =IFERROR(('Historical IFS Trent Ltd'!F27+'Historical IFS Trent Ltd'!F21)/'Historical IFS Trent Ltd'!F21,0) -> 1.0697118 | G25: =IFERROR(('Historical IFS Trent Ltd'!G27+'Historical IFS Trent Ltd'!G21)/'Historical IFS Trent Ltd'!G21,0) -> -0.54998274 | H25: =IFERROR(('Historical IFS Trent Ltd'!H27+'Historical IFS Trent Ltd'!H21)/'Historical IFS Trent Ltd'!H21,0) -> 0.87396872 | I25: =IFERROR(('Historical IFS Trent Ltd'!I27+'Historical IFS Trent Ltd'!I21)/'Historical IFS Trent Ltd'!I21,0) -> 1.5170542 | J25: =IFERROR(('Historical IFS Trent Ltd'!J27+'Historical IFS Trent Ltd'!J21)/'Historical IFS Trent Ltd'!J21,0) -> 3.5347332 | ... L25: =IFERROR(('Historical IFS Trent Ltd'!L27+'Historical IFS Trent Ltd'!L21)/'Historical IFS Trent Ltd'!L21,0) -> 13.734482 | N25: =IFERROR(AVERAGE(C25:L25),0) -> 3.9278196 | O25: =IFERROR(AVERAGE(D25:M25),0) -> 4.1392409
B27: Debtor Turnover Ratio | C27: =IFERROR('Historical IFS Trent Ltd'!C6/'Historical IFS Trent Ltd'!C59,0) -> 306.15541 | D27: =IFERROR('Historical IFS Trent Ltd'!D6/'Historical IFS Trent Ltd'!D59,0) -> 142.87815 | E27: =IFERROR('Historical IFS Trent Ltd'!E6/'Historical IFS Trent Ltd'!E59,0) -> 159.02297 | F27: =IFERROR('Historical IFS Trent Ltd'!F6/'Historical IFS Trent Ltd'!F59,0) -> 203.62033 | G27: =IFERROR('Historical IFS Trent Ltd'!G6/'Historical IFS Trent Ltd'!G59,0) -> 124.8416 | H27: =IFERROR('Historical IFS Trent Ltd'!H6/'Historical IFS Trent Ltd'!H59,0) -> 246.33187 | I27: =IFERROR('Historical IFS Trent Ltd'!I6/'Historical IFS Trent Ltd'!I59,0) -> 239.66327 | J27: =IFERROR('Historical IFS Trent Ltd'!J6/'Historical IFS Trent Ltd'!J59,0) -> 151.39601 | ... L27: =IFERROR('Historical IFS Trent Ltd'!L6/'Historical IFS Trent Ltd'!L59,0) -> 392.53442 | N27: =IFERROR(AVERAGE(C27:L27),0) -> 223.8638 | O27: =IFERROR(AVERAGE(D27:M27),0) -> 214.72029
B28: Creditor Turnover Ratio | C28: =IFERROR('Historical IFS Trent Ltd'!C6/'Historical IFS Trent Ltd'!C50,0) -> 6.4084577 | D28: =IFERROR('Historical IFS Trent Ltd'!D6/'Historical IFS Trent Ltd'!D50,0) -> 6.1807712 | E28: =IFERROR('Historical IFS Trent Ltd'!E6/'Historical IFS Trent Ltd'!E50,0) -> 6.2907847 | F28: =IFERROR('Historical IFS Trent Ltd'!F6/'Historical IFS Trent Ltd'!F50,0) -> 1.2365271 | G28: =IFERROR('Historical IFS Trent Ltd'!G6/'Historical IFS Trent Ltd'!G50,0) -> 5.7998971 | H28: =IFERROR('Historical IFS Trent Ltd'!H6/'Historical IFS Trent Ltd'!H50,0) -> 7.0650269 | I28: =IFERROR('Historical IFS Trent Ltd'!I6/'Historical IFS Trent Ltd'!I50,0) -> 8.065388 | J28: =IFERROR('Historical IFS Trent Ltd'!J6/'Historical IFS Trent Ltd'!J50,0) -> 9.2281323 | ... L28: =IFERROR('Historical IFS Trent Ltd'!L6/'Historical IFS Trent Ltd'!L50,0) -> 9.1971732 | N28: =IFERROR(AVERAGE(C28:L28),0) -> 6.943003 | O28: =IFERROR(AVERAGE(D28:M28),0) -> 7.0023969
B29: Inventory Turnover | C29: =IFERROR('Historical IFS Trent Ltd'!C6/'Historical IFS Trent Ltd'!C60,0) -> 5.9354205 | D29: =IFERROR('Historical IFS Trent Ltd'!D6/'Historical IFS Trent Ltd'!D60,0) -> 6.257679 | E29: =IFERROR('Historical IFS Trent Ltd'!E6/'Historical IFS Trent Ltd'!E60,0) -> 5.2921269 | F29: =IFERROR('Historical IFS Trent Ltd'!F6/'Historical IFS Trent Ltd'!F60,0) -> 5.735312 | G29: =IFERROR('Historical IFS Trent Ltd'!G6/'Historical IFS Trent Ltd'!G60,0) -> 6.0528024 | H29: =IFERROR('Historical IFS Trent Ltd'!H6/'Historical IFS Trent Ltd'!H60,0) -> 5.1833644 | I29: =IFERROR('Historical IFS Trent Ltd'!I6/'Historical IFS Trent Ltd'!I60,0) -> 6.0551441 | J29: =IFERROR('Historical IFS Trent Ltd'!J6/'Historical IFS Trent Ltd'!J60,0) -> 7.8188383 | ... L29: =IFERROR('Historical IFS Trent Ltd'!L6/'Historical IFS Trent Ltd'!L60,0) -> 8.7698219 | N29: =IFERROR(AVERAGE(C29:L29),0) -> 6.5479087 | O29: =IFERROR(AVERAGE(D29:M29),0) -> 6.615963
B30: Fixed Asset Turnover | C30: =IFERROR('Historical IFS Trent Ltd'!C6/'Historical IFS Trent Ltd'!C53,0) -> 3.3030927 | D30: =IFERROR('Historical IFS Trent Ltd'!D6/'Historical IFS Trent Ltd'!D53,0) -> 3.5222112 | E30: =IFERROR('Historical IFS Trent Ltd'!E6/'Historical IFS Trent Ltd'!E53,0) -> 3.9720922 | F30: =IFERROR('Historical IFS Trent Ltd'!F6/'Historical IFS Trent Ltd'!F53,0) -> 1.2729849 | G30: =IFERROR('Historical IFS Trent Ltd'!G6/'Historical IFS Trent Ltd'!G53,0) -> 0.84908737 | H30: =IFERROR('Historical IFS Trent Ltd'!H6/'Historical IFS Trent Ltd'!H53,0) -> 0.95973935 | I30: =IFERROR('Historical IFS Trent Ltd'!I6/'Historical IFS Trent Ltd'!I53,0) -> 1.8206563 | J30: =IFERROR('Historical IFS Trent Ltd'!J6/'Historical IFS Trent Ltd'!J53,0) -> 5.0512302 | ... L30: =IFERROR('Historical IFS Trent Ltd'!L6/'Historical IFS Trent Ltd'!L53,0) -> 3.6374625 | N30: =IFERROR(AVERAGE(C30:L30),0) -> 2.878754 | O30: =IFERROR(AVERAGE(D30:M30),0) -> 2.8316052
B31: Capital Turnover Ratio | C31: =IFERROR('Historical IFS Trent Ltd'!C6/SUM('Historical IFS Trent Ltd'!C47:C48),0) -> 1.1710614 | D31: =IFERROR('Historical IFS Trent Ltd'!D6/SUM('Historical IFS Trent Ltd'!D47:D48),0) -> 1.3523258 | E31: =IFERROR('Historical IFS Trent Ltd'!E6/SUM('Historical IFS Trent Ltd'!E47:E48),0) -> 1.5974637 | F31: =IFERROR('Historical IFS Trent Ltd'!F6/SUM('Historical IFS Trent Ltd'!F47:F48),0) -> 1.4599312 | G31: =IFERROR('Historical IFS Trent Ltd'!G6/SUM('Historical IFS Trent Ltd'!G47:G48),0) -> 1.1210231 | H31: =IFERROR('Historical IFS Trent Ltd'!H6/SUM('Historical IFS Trent Ltd'!H47:H48),0) -> 1.9027157 | I31: =IFERROR('Historical IFS Trent Ltd'!I6/SUM('Historical IFS Trent Ltd'!I47:I48),0) -> 3.175516 | J31: =IFERROR('Historical IFS Trent Ltd'!J6/SUM('Historical IFS Trent Ltd'!J47:J48),0) -> 3.0422569 | ... L31: =IFERROR('Historical IFS Trent Ltd'!L6/SUM('Historical IFS Trent Ltd'!L47:L48),0) -> 2.8740343 | N31: =IFERROR(AVERAGE(C31:L31),0) -> 2.0833535 | O31: =IFERROR(AVERAGE(D31:M31),0) -> 2.1847193
B33: Debtor Days | C33: =IFERROR(365/C27,0) -> 1.192205 | D33: =IFERROR(365/D27,0) -> 2.5546244 | E33: =IFERROR(365/E27,0) -> 2.2952658 | F33: =IFERROR(365/F27,0) -> 1.7925519 | G33: =IFERROR(365/G27,0) -> 2.923705 | H33: =IFERROR(365/H27,0) -> 1.4817409 | I33: =IFERROR(365/I27,0) -> 1.5229701 | J33: =IFERROR(365/J27,0) -> 2.4108957 | ... L33: =IFERROR(365/L27,0) -> 0.92985477 | N33: =IFERROR(AVERAGE(C33:L33),0) -> 1.8444769 | O33: =IFERROR(AVERAGE(D33:M33),0) -> 1.9169516
B34: Payable Days | C34: =IFERROR(365/C28,0) -> 56.955982 | D34: =IFERROR(365/D28,0) -> 59.054119 | E34: =IFERROR(365/E28,0) -> 58.021378 | F34: =IFERROR(365/F28,0) -> 295.18157 | G34: =IFERROR(365/G28,0) -> 62.932151 | H34: =IFERROR(365/H28,0) -> 51.662932 | I34: =IFERROR(365/I28,0) -> 45.255107 | J34: =IFERROR(365/J28,0) -> 39.552966 | ... L34: =IFERROR(365/L28,0) -> 39.686107 | N34: =IFERROR(AVERAGE(C34:L34),0) -> 74.495673 | O34: =IFERROR(AVERAGE(D34:M34),0) -> 76.444528
B35: Inventory Days | C35: =IFERROR(365/C29,0) -> 61.495222 | D35: =IFERROR(365/D29,0) -> 58.328335 | E35: =IFERROR(365/E29,0) -> 68.970379 | F35: =IFERROR(365/F29,0) -> 63.640827 | G35: =IFERROR(365/G29,0) -> 60.302646 | H35: =IFERROR(365/H29,0) -> 70.417584 | I35: =IFERROR(365/I29,0) -> 60.279325 | J35: =IFERROR(365/J29,0) -> 46.682126 | ... L35: =IFERROR(365/L29,0) -> 41.620001 | N35: =IFERROR(AVERAGE(C35:L35),0) -> 57.529993 | O35: =IFERROR(AVERAGE(D35:M35),0) -> 57.089412
B36: Cash Conversion Cycle | C36: =IFERROR(SUM(C33,C35)-C34,0) -> 5.7314449 | D36: =IFERROR(SUM(D33,D35)-D34,0) -> 1.8288404 | E36: =IFERROR(SUM(E33,E35)-E34,0) -> 13.244267 | F36: =IFERROR(SUM(F33,F35)-F34,0) -> -229.74819 | G36: =IFERROR(SUM(G33,G35)-G34,0) -> 0.29420045 | H36: =IFERROR(SUM(H33,H35)-H34,0) -> 20.236393 | I36: =IFERROR(SUM(I33,I35)-I34,0) -> 16.547187 | J36: =IFERROR(SUM(J33,J35)-J34,0) -> 9.5400566 | ... L36: =IFERROR(SUM(L33,L35)-L34,0) -> 2.8637491 | N36: =IFERROR(AVERAGE(C36:L36),0) -> -15.121203 | O36: =IFERROR(AVERAGE(D36:M36),0) -> -17.438164
B38: CFO/Sales | C38: =IFERROR('Historical IFS Trent Ltd'!C78/'Historical IFS Trent Ltd'!C6,0) -> 0.05738121 | D38: =IFERROR('Historical IFS Trent Ltd'!D78/'Historical IFS Trent Ltd'!D6,0) -> 0.036153625 | E38: =IFERROR('Historical IFS Trent Ltd'!E78/'Historical IFS Trent Ltd'!E6,0) -> 0.0079840623 | F38: =IFERROR('Historical IFS Trent Ltd'!F78/'Historical IFS Trent Ltd'!F6,0) -> 0.10355768 | G38: =IFERROR('Historical IFS Trent Ltd'!G78/'Historical IFS Trent Ltd'!G6,0) -> 0.109913 | H38: =IFERROR('Historical IFS Trent Ltd'!H78/'Historical IFS Trent Ltd'!H6,0) -> 0.012672242 | I38: =IFERROR('Historical IFS Trent Ltd'!I78/'Historical IFS Trent Ltd'!I6,0) -> 0.072191041 | J38: =IFERROR('Historical IFS Trent Ltd'!J78/'Historical IFS Trent Ltd'!J6,0) -> 0.10892832 | ... L38: =IFERROR('Historical IFS Trent Ltd'!L78/'Historical IFS Trent Ltd'!L6,0) -> 0.13290685 | N38: =IFERROR(AVERAGE(C38:L38),0) -> 0.073862633 | O38: =IFERROR(AVERAGE(D38:M38),0) -> 0.075693902
B39: CFO/Total Assets | C39: =IFERROR('Historical IFS Trent Ltd'!C78/'Historical IFS Trent Ltd'!C64,0) -> 0.046799415 | D39: =IFERROR('Historical IFS Trent Ltd'!D78/'Historical IFS Trent Ltd'!D64,0) -> 0.033392412 | E39: =IFERROR('Historical IFS Trent Ltd'!E78/'Historical IFS Trent Ltd'!E64,0) -> 0.0082071003 | F39: =IFERROR('Historical IFS Trent Ltd'!F78/'Historical IFS Trent Ltd'!F64,0) -> 0.065556742 | G39: =IFERROR('Historical IFS Trent Ltd'!G78/'Historical IFS Trent Ltd'!G64,0) -> 0.049792705 | H39: =IFERROR('Historical IFS Trent Ltd'!H78/'Historical IFS Trent Ltd'!H64,0) -> 0.0073776666 | I39: =IFERROR('Historical IFS Trent Ltd'!I78/'Historical IFS Trent Ltd'!I64,0) -> 0.073624673 | J39: =IFERROR('Historical IFS Trent Ltd'!J78/'Historical IFS Trent Ltd'!J64,0) -> 0.18822215 | ... L39: =IFERROR('Historical IFS Trent Ltd'!L78/'Historical IFS Trent Ltd'!L64,0) -> 0.22747852 | N39: =IFERROR(AVERAGE(C39:L39),0) -> 0.087678509 | O39: =IFERROR(AVERAGE(D39:M39),0) -> 0.09222063
B40: CFO/Total Debt | C40: =IFERROR('Historical IFS Trent Ltd'!C78/'Historical IFS Trent Ltd'!C49,0) -> 0.26548221 | D40: =IFERROR('Historical IFS Trent Ltd'!D78/'Historical IFS Trent Ltd'!D49,0) -> 0.19926935 | E40: =IFERROR('Historical IFS Trent Ltd'!E78/'Historical IFS Trent Ltd'!E49,0) -> 0.042498077 | F40: =IFERROR('Historical IFS Trent Ltd'!F78/'Historical IFS Trent Ltd'!F49,0) -> 1.2043771 | G40: =IFERROR('Historical IFS Trent Ltd'!G78/'Historical IFS Trent Ltd'!G49,0) -> 0.096165851 | H40: =IFERROR('Historical IFS Trent Ltd'!H78/'Historical IFS Trent Ltd'!H49,0) -> 0.012062573 | I40: =IFERROR('Historical IFS Trent Ltd'!I78/'Historical IFS Trent Ltd'!I49,0) -> 0.13328435 | J40: =IFERROR('Historical IFS Trent Ltd'!J78/'Historical IFS Trent Ltd'!J49,0) -> 0.76897187 | ... L40: =IFERROR('Historical IFS Trent Ltd'!L78/'Historical IFS Trent Ltd'!L49,0) -> 1.0416789 | N40: =IFERROR(AVERAGE(C40:L40),0) -> 0.45062395 | O40: =IFERROR(AVERAGE(D40:M40),0) -> 0.47119526

Sheet Dupont Analysis
B2: ='Raw Data Trent Ltd'!B1 -> TRENT LTD
B3: =CONCATENATE(" (",VLOOKUP(B2,'[1]List of Stocks'!A2:C5442,3,1)," | ","BSE Code: ",VLOOKUP(B2,'[1]List of Stocks'!A2:B5442,2,1),")") -> (TRENT | BSE Code: 500251)
B4: INR 3997.6
B5: 52 Week (High - INR6261 & Low-3276)
B7: About the Company
B8: Trent Limited, originally incorporated as Lakme Limited on December 5, 1952, was initially in the business of cosmetics, toiletries, and perfumery products. In 1998, the company divested from cosmetics and shifted focus to apparel and lifestyle retailing, establishing Trent as a strong presence in India’s retail sector. The company is headquartered in Mumbai and is a publicly listed entity under the Tata Group. Its growth is primarily driven by Zudio’s strong demand, high inventory turnover, and efficient store economics, which have helped improve profitability and generate strong returns on equity through operational efficiency rather than heavy debt usage.
B13: Financial Summary
B65: Return on Equity (ROE)
C66: ='Raw Data Trent Ltd'!C16 -> 43190 | D66: ='Raw Data Trent Ltd'!D16 -> 43555 | E66: ='Raw Data Trent Ltd'!E16 -> 43921 | F66: ='Raw Data Trent Ltd'!F16 -> 44286 | G66: ='Raw Data Trent Ltd'!G16 -> 44651 | H66: ='Raw Data Trent Ltd'!H16 -> 45016 | I66: ='Raw Data Trent Ltd'!I16 -> 45382 | J66: ='Raw Data Trent Ltd'!J16 -> 45747 | K66: ='Raw Data Trent Ltd'!K16 -> 46112
B67: Net Profit | C67: ='Raw Data Trent Ltd'!C30 -> 86.97 | D67: ='Raw Data Trent Ltd'!D30 -> 96.96 | E67: ='Raw Data Trent Ltd'!E30 -> 122.85 | F67: ='Raw Data Trent Ltd'!F30 -> -146.17 | G67: ='Raw Data Trent Ltd'!G30 -> 105.83 | H67: ='Raw Data Trent Ltd'!H30 -> 444.63 | I67: ='Raw Data Trent Ltd'!I30 -> 1486.8 | J67: ='Raw Data Trent Ltd'!J30 -> 1546.72 | K67: ='Raw Data Trent Ltd'!K30 -> 1719.65
B68: Average Shareholder Equity | C68: =(('Raw Data Trent Ltd'!D57+'Raw Data Trent Ltd'!D58)+('Raw Data Trent Ltd'!C57+'Raw Data Trent Ltd'!C58))/2 -> 1620.94 | D68: =(('Raw Data Trent Ltd'!E57+'Raw Data Trent Ltd'!E58)+('Raw Data Trent Ltd'!D57+'Raw Data Trent Ltd'!D58))/2 -> 2017.14 | E68: =(('Raw Data Trent Ltd'!F57+'Raw Data Trent Ltd'!F58)+('Raw Data Trent Ltd'!E57+'Raw Data Trent Ltd'!E58))/2 -> 2350.4 | F68: =(('Raw Data Trent Ltd'!G57+'Raw Data Trent Ltd'!G58)+('Raw Data Trent Ltd'!F57+'Raw Data Trent Ltd'!F58))/2 -> 2338.515 | G68: =(('Raw Data Trent Ltd'!H57+'Raw Data Trent Ltd'!H58)+('Raw Data Trent Ltd'!G57+'Raw Data Trent Ltd'!G58))/2 -> 2479.745 | H68: =(('Raw Data Trent Ltd'!I57+'Raw Data Trent Ltd'!I58)+('Raw Data Trent Ltd'!H57+'Raw Data Trent Ltd'!H58))/2 -> 3331.615 | I68: =(('Raw Data Trent Ltd'!J57+'Raw Data Trent Ltd'!J58)+('Raw Data Trent Ltd'!I57+'Raw Data Trent Ltd'!I58))/2 -> 4764.74 | J68: =(('Raw Data Trent Ltd'!K57+'Raw Data Trent Ltd'!K58)+('Raw Data Trent Ltd'!J57+'Raw Data Trent Ltd'!J58))/2 -> 6223.21 | K68: =(('Raw Data Trent Ltd'!L57+'Raw Data Trent Ltd'!L58)+('Raw Data Trent Ltd'!K57+'Raw Data Trent Ltd'!K58))/2 -> 3492.34
B69: Return on Equity | C69: =C67/C68 -> 0.053654053 | D69: =D67/D68 -> 0.048068057 | E69: =E67/E68 -> 0.052267699 | F69: =F67/F68 -> -0.062505479 | G69: =G67/G68 -> 0.042677775 | H69: =H67/H68 -> 0.1334578 | I69: =I67/I68 -> 0.31204221 | J69: =J67/J68 -> 0.24854054 | K69: =K67/K68 -> 0.49240624
B71: ROE - Dupont Equation
C72: =C66 -> 43190 | D72: =D66 -> 43555 | E72: =E66 -> 43921 | F72: =F66 -> 44286 | G72: =G66 -> 44651 | H72: =H66 -> 45016 | I72: =I66 -> 45382 | J72: =J66 -> 45747 | K72: =K66 -> 46112
B73: =B67 -> Net Profit | C73: =C67 -> 86.97 | D73: =D67 -> 96.96 | E73: =E67 -> 122.85 | F73: =F67 -> -146.17 | G73: =G67 -> 105.83 | H73: =H67 -> 444.63 | I73: =I67 -> 1486.8 | ... K73: =K67 -> 1719.65
B74: Revenue | C74: ='Raw Data Trent Ltd'!C17 -> 2157.46 | D74: ='Raw Data Trent Ltd'!D17 -> 2630.24 | E74: ='Raw Data Trent Ltd'!E17 -> 3485.98 | F74: ='Raw Data Trent Ltd'!F17 -> 2592.96 | G74: ='Raw Data Trent Ltd'!G17 -> 4498.02 | H74: ='Raw Data Trent Ltd'!H17 -> 8242.02 | I74: ='Raw Data Trent Ltd'!I17 -> 12375.11 | J74: ='Raw Data Trent Ltd'!J17 -> 17134.61 | K74: ='Raw Data Trent Ltd'!K17 -> 20074.21
B75: Net Profit Margin (A) | C75: =C73/C74 -> 0.040311292 | D75: =D73/D74 -> 0.036863556 | E75: =E73/E74 -> 0.035241166 | F75: =F73/F74 -> -0.056371868 | G75: =G73/G74 -> 0.02352813 | H75: =H73/H74 -> 0.053946727 | I75: =I73/I74 -> 0.12014439 | J75: =J73/J74 -> 0.09026876 | K75: =K73/K74 -> 0.085664641
B77: Revenue | C77: =C74 -> 2157.46 | D77: =D74 -> 2630.24 | E77: =E74 -> 3485.98 | F77: =F74 -> 2592.96 | G77: =G74 -> 4498.02 | H77: =H74 -> 8242.02 | I77: =I74 -> 12375.11 | J77: =J74 -> 17134.61 | K77: =K74 -> 20074.21
B78: Average Total Asset | C78: =('Raw Data Trent Ltd'!D66+'Raw Data Trent Ltd'!C66)/2 -> 2447.31 | D78: =('Raw Data Trent Ltd'!E66+'Raw Data Trent Ltd'!D66)/2 -> 4032.72 | E78: =('Raw Data Trent Ltd'!F66+'Raw Data Trent Ltd'!E66)/2 -> 5615.205 | F78: =('Raw Data Trent Ltd'!G66+'Raw Data Trent Ltd'!F66)/2 -> 6724.875 | G78: =('Raw Data Trent Ltd'!H66+'Raw Data Trent Ltd'!G66)/2 -> 7903.775 | H78: =('Raw Data Trent Ltd'!I66+'Raw Data Trent Ltd'!H66)/2 -> 7621.64 | I78: =('Raw Data Trent Ltd'!J66+'Raw Data Trent Ltd'!I66)/2 -> 8290.695 | J78: =('Raw Data Trent Ltd'!K66+'Raw Data Trent Ltd'!J66)/2 -> 10574.11 | K78: =('Raw Data Trent Ltd'!L66+'Raw Data Trent Ltd'!K66)/2 -> 5864.29
B79: Asset Turnover Ratio (B) | C79: =C77/C78 -> 0.88156384 | D79: =D77/D78 -> 0.6522248 | E79: =E77/E78 -> 0.62081082 | F79: =F77/F78 -> 0.38557743 | G79: =G77/G78 -> 0.56909768 | H79: =H77/H78 -> 1.0813972 | I79: =I77/I78 -> 1.4926505 | J79: =J77/J78 -> 1.6204305 | K79: =K77/K78 -> 3.4231271
B81: Average Total Asset | C81: =C78 -> 2447.31 | D81: =D78 -> 4032.72 | E81: =E78 -> 5615.205 | F81: =F78 -> 6724.875 | G81: =G78 -> 7903.775 | H81: =H78 -> 7621.64 | I81: =I78 -> 8290.695 | J81: =J78 -> 10574.11 | K81: =K78 -> 5864.29
B82: Average Shareholder Equity | C82: =C68 -> 1620.94 | D82: =D68 -> 2017.14 | E82: =E68 -> 2350.4 | F82: =F68 -> 2338.515 | G82: =G68 -> 2479.745 | H82: =H68 -> 3331.615 | I82: =I68 -> 4764.74 | J82: =J68 -> 6223.21 | K82: =K68 -> 3492.34
B83: Equity Multiplier (C) | C83: =C81/C82 -> 1.5098091 | D83: =D81/D82 -> 1.9992266 | E83: =E81/E82 -> 2.3890423 | F83: =F81/F82 -> 2.8757032 | G83: =G81/G82 -> 3.1873338 | H83: =H81/H82 -> 2.2876713 | I83: =I81/I82 -> 1.7400099 | J83: =J81/J82 -> 1.6991408 | K83: =K81/K82 -> 1.6791864
B85: Return on Equity (A*B*C) | C85: =C83*C79*C75 -> 0.053654053 | D85: =D83*D79*D75 -> 0.048068057 | E85: =E83*E79*E75 -> 0.052267699 | F85: =F83*F79*F75 -> -0.062505479 | G85: =G83*G79*G75 -> 0.042677775 | H85: =H83*H79*H75 -> 0.1334578 | I85: =I83*I79*I75 -> 0.31204221 | J85: =J83*J79*J75 -> 0.24854054 | K85: =K83*K79*K75 -> 0.49240624
B87: Return on Asset
C88: =C66 -> 43190 | D88: =D66 -> 43555 | E88: =E66 -> 43921 | F88: =F66 -> 44286 | G88: =G66 -> 44651 | H88: =H66 -> 45016 | I88: =I66 -> 45382 | J88: =J66 -> 45747 | K88: =K66 -> 46112
B89: Net Profit | C89: =C73 -> 86.97 | D89: =D73 -> 96.96 | E89: =E73 -> 122.85 | F89: =F73 -> -146.17 | G89: =G73 -> 105.83 | H89: =H73 -> 444.63 | I89: =I73 -> 1486.8 | J89: =J73 -> 1546.72 | K89: =K73 -> 1719.65
B90: Avg Total Asset | C90: =C78 -> 2447.31 | D90: =D78 -> 4032.72 | E90: =E78 -> 5615.205 | F90: =F78 -> 6724.875 | G90: =G78 -> 7903.775 | H90: =H78 -> 7621.64 | I90: =I78 -> 8290.695 | J90: =J78 -> 10574.11 | K90: =K78 -> 5864.29
B91: Return on Equity | C91: =C89/C90 -> 0.035536977 | D91: =D89/D90 -> 0.024043326 | E91: =E89/E90 -> 0.021878097 | F91: =F89/F90 -> -0.02173572 | G91: =G89/G90 -> 0.013389804 | H91: =H89/H90 -> 0.058337838 | I91: =I89/I90 -> 0.17933358 | J91: =J89/J90 -> 0.14627425 | K91: =K89/K90 -> 0.29324096
B93: ROA - Dupont Equation
C94: =C88 -> 43190 | D94: =D88 -> 43555 | E94: =E88 -> 43921 | F94: =F88 -> 44286 | G94: =G88 -> 44651 | H94: =H88 -> 45016 | I94: =I88 -> 45382 | J94: =J88 -> 45747 | K94: =K88 -> 46112
B95: =B89 -> Net Profit | C95: =C73 -> 86.97 | D95: =D73 -> 96.96 | E95: =E73 -> 122.85 | F95: =F73 -> -146.17 | G95: =G73 -> 105.83 | H95: =H73 -> 444.63 | I95: =I73 -> 1486.8 | J95: =J73 -> 1546.72 | K95: =K73 -> 1719.65
B96: Revenue | C96: =C74 -> 2157.46 | D96: =D74 -> 2630.24 | E96: =E74 -> 3485.98 | F96: =F74 -> 2592.96 | G96: =G74 -> 4498.02 | H96: =H74 -> 8242.02 | I96: =I74 -> 12375.11 | J96: =J74 -> 17134.61 | K96: =K74 -> 20074.21
B97: Net Profit Margin (A) | C97: =C95/C96 -> 0.040311292 | D97: =D95/D96 -> 0.036863556 | E97: =E95/E96 -> 0.035241166 | F97: =F95/F96 -> -0.056371868 | G97: =G95/G96 -> 0.02352813 | H97: =H95/H96 -> 0.053946727 | I97: =I95/I96 -> 0.12014439 | J97: =J95/J96 -> 0.09026876 | K97: =K95/K96 -> 0.085664641
B99: Revenue | C99: =C77 -> 2157.46 | D99: =D77 -> 2630.24 | E99: =E77 -> 3485.98 | F99: =F77 -> 2592.96 | G99: =G77 -> 4498.02 | H99: =H77 -> 8242.02 | I99: =I77 -> 12375.11 | J99: =J77 -> 17134.61 | K99: =K77 -> 20074.21
B100: Average Total Asset | C100: =C78 -> 2447.31 | D100: =D78 -> 4032.72 | E100: =E78 -> 5615.205 | F100: =F78 -> 6724.875 | G100: =G78 -> 7903.775 | H100: =H78 -> 7621.64 | I100: =I78 -> 8290.695 | J100: =J78 -> 10574.11 | K100: =K78 -> 5864.29
B101: Asset Turnover Ratio (B) | C101: =C99/C100 -> 0.88156384 | D101: =D99/D100 -> 0.6522248 | E101: =E99/E100 -> 0.62081082 | F101: =F99/F100 -> 0.38557743 | G101: =G99/G100 -> 0.56909768 | H101: =H99/H100 -> 1.0813972 | I101: =I99/I100 -> 1.4926505 | J101: =J99/J100 -> 1.6204305 | K101: =K99/K100 -> 3.4231271
B103: Return on Asset (A*B) | C103: =C97*C101 -> 0.035536977 | D103: =D97*D101 -> 0.024043326 | E103: =E97*E101 -> 0.021878097 | F103: =F97*F101 -> -0.02173572 | G103: =G97*G101 -> 0.013389804 | H103: =H97*H101 -> 0.058337838 | I103: =I97*I101 -> 0.17933358 | J103: =J97*J101 -> 0.14627425 | K103: =K97*K101 -> 0.29324096

Sheet VAR Trent Ltd
A2: # | B2: Date | C2: Adj Close | D2: Return | E2: Sorted Returns | G2: Replication | H2: Simulated Returns | J2: ="Calculation of VAR - "&'Raw Data Trent Ltd'!$B$1&" (Historical Approach)" -> Calculation of VAR - TRENT LTD (Historical Approach)
B3: 45330 | C3: 3778.525 | D3: =(C3-C4)/C4 -> 15.20815 | E3: 0.14679727 | G3: 1 | H3: =_xlfn.NORM.INV(RAND(),$N$4,$N$5) -> 0.023878557 | J3: Historical Approach
B4: 42759 | C4: 233.125 | D4: =(C4-C5)/C5 -> -0.63165587 | E4: 0.11770346 | G4: 2 | H4: =_xlfn.NORM.INV(RAND(),$N$4,$N$5) -> -0.001361594 | J4: Mean | N4: =AVERAGE(E3:E2320) -> 0.0014988706
B5: 44005 | C5: 632.9 | D5: =(C5-C6)/C6 -> -0.025107825 | E5: 0.095646153 | G5: 3 | H5: =_xlfn.NORM.INV(RAND(),$N$4,$N$5) -> -0.010738577 | J5: Std Deviation | N5: =_xlfn.STDEV.S(E3:E2320) -> 0.019995721
B6: 43868 | C6: 649.2 | D6: =(C6-C7)/C7 -> 0.50924096 | E6: 0.091918258 | G6: 4 | H6: =_xlfn.NORM.INV(RAND(),$N$4,$N$5) -> 0.029447754 | J6: Min | N6: =MIN(E3:E2320) -> -0.15471315
B7: 43915 | C7: 430.15 | D7: =(C7-C8)/C8 -> -0.14111716 | E7: 0.088987342 | G7: 5 | H7: =_xlfn.NORM.INV(RAND(),$N$4,$N$5) -> -0.030403713 | J7: Max | N7: =MAX(E3:E2320) -> 0.14679727
B8: 43917 | C8: 500.825 | D8: =(C8-C9)/C9 -> 0.75666433 | E8: 0.084917411 | G8: 6 | H8: =_xlfn.NORM.INV(RAND(),$N$4,$N$5) -> -0.0075561029 | J8: Current MP | N8: 4101.3
B9: 42948 | C9: 285.1 | D9: =(C9-C10)/C10 -> -0.92401791 | E9: 0.083824368 | G9: 7 | H9: =_xlfn.NORM.INV(RAND(),$N$4,$N$5) -> -0.01439619
B10: 46118 | C10: 3752.2 | D10: =(C10-C11)/C11 -> 6.7154166 | E10: 0.07704231 | G10: 8 | H10: =_xlfn.NORM.INV(RAND(),$N$4,$N$5) -> -0.0076468711 | J10: Percentile | K10: Confidence | L10: VAR% | M10: Stock Price | N10: VAR (INR)
B11: 43910 | C11: 486.325 | D11: =(C11-C12)/C12 -> -0.14285085 | E11: 0.074157924 | G11: 9 | H11: =_xlfn.NORM.INV(RAND(),$N$4,$N$5) -> -0.002643682 | J11: 0.05 | K11: =100%-J11 -> 0.95 | L11: =_xlfn.PERCENTILE.INC($E$3:$E$2120,J11) -> -0.016036082 | M11: =$N$8*(1+L11) -> 4035.5312 | N11: =M11-$N$8 -> -65.768784
B12: 43985 | C12: 567.375 | D12: =(C12-C13)/C13 -> 0.22908205 | E12: 0.073557237 | G12: 10 | H12: =_xlfn.NORM.INV(RAND(),$N$4,$N$5) -> 0.014828984 | J12: 0.01 | K12: =100%-J12 -> 0.99 | L12: =_xlfn.PERCENTILE.INC($E$3:$E$2120,J12) -> -0.020064022 | M12: =$N$8*(1+L12) -> 4019.0114 | N12: =M12-$N$8 -> -82.288574
B13: 43916 | C13: 461.625 | D13: =(C13-C14)/C14 -> -0.85989499 | E13: 0.073172149 | G13: 11 | H13: =_xlfn.NORM.INV(RAND(),$N$4,$N$5) -> -0.0012165222 | J13: 0.005 | K13: =100%-J13 -> 0.995 | L13: =_xlfn.PERCENTILE.INC($E$3:$E$2120,J13) -> -0.020388353 | M13: =$N$8*(1+L13) -> 4017.6812 | N13: =M13-$N$8 -> -83.618752
B14: 45329 | C14: 3294.85 | D14: =(C14-C15)/C15 -> 5.6294769 | E14: 0.072708182 | G14: 12 | H14: =_xlfn.NORM.INV(RAND(),$N$4,$N$5) -> 0.033183214 | J14: 0.1 | K14: =100%-J14 -> 0.9 | L14: =_xlfn.PERCENTILE.INC($E$3:$E$2120,J14) -> -0.013205806 | M14: =$N$8*(1+L14) -> 4047.139 | N14: =M14-$N$8 -> -54.160971
B15: 43983 | C15: 497 | D15: =(C15-C16)/C16 -> -0.91716977 | E15: 0.0721605 | G15: 13 | H15: =_xlfn.NORM.INV(RAND(),$N$4,$N$5) -> 0.01425464
B16: 45513 | C16: 6000.225 | D16: =(C16-C17)/C17 -> 23.123932 | E16: 0.069806729 | G16: 14 | H16: =_xlfn.NORM.INV(RAND(),$N$4,$N$5) -> -0.010916203
B17: 42760 | C17: 248.725 | D17: =(C17-C18)/C18 -> -0.80946453 | E17: 0.06691689 | G17: 15 | H17: =_xlfn.NORM.INV(RAND(),$N$4,$N$5) -> 0.018484125 | J17: ="Calculation of VAR - "&'Raw Data Trent Ltd'!$B$1&" (Monte Carlo Approach)" -> Calculation of VAR - TRENT LTD (Monte Carlo Approach)
B18: 44966 | C18: 1305.4 | D18: =(C18-C19)/C19 -> 0.7737618 | E18: 0.065632653 | G18: 16 | H18: =_xlfn.NORM.INV(RAND(),$N$4,$N$5) -> 0.045264126 | J18: Monte Carlo Approach
B19: 44146 | C19: 735.95 | D19: =(C19-C20)/C20 -> -0.84434715 | E19: 0.065281899 | G19: 17 | H19: =_xlfn.NORM.INV(RAND(),$N$4,$N$5) -> -0.015500478 | J19: Mean | N19: =AVERAGE($H$3:$H$2120) -> 0.0016053987
B20: 45448 | C20: 4728.15 | D20: =(C20-C21)/C21 -> 4.3974315 | E20: 0.064778741 | G20: 18 | H20: =_xlfn.NORM.INV(RAND(),$N$4,$N$5) -> 0.026794594 | J20: Std Deviation | N20: =_xlfn.STDEV.S($H$3:$H$2120) -> 0.019873109
B21: 44257 | C21: 876 | D21: =(C21-C22)/C22 -> 0.65752129 | E21: 0.064042999 | G21: 19 | H21: =_xlfn.NORM.INV(RAND(),$N$4,$N$5) -> 0.023965169 | J21: Min | N21: =MIN($H$3:$H$2120) -> -0.072512852
B22: 43984 | C22: 528.5 | D22: =(C22-C23)/C23 -> 0.57291667 | E22: 0.063380282 | G22: 20 | H22: =_xlfn.NORM.INV(RAND(),$N$4,$N$5) -> -0.0252423 | J22: Max | N22: =MAX($H$3:$H$2120) -> 0.068463723
B23: 43291 | C23: 336 | D23: =(C23-C24)/C24 -> 0.31442543 | E23: 0.0628707 | G23: 21 | H23: =_xlfn.NORM.INV(RAND(),$N$4,$N$5) -> -0.0084223952 | J23: Current MP | N23: =N8 -> 4101.3
B24: 42923 | C24: 255.625 | D24: =(C24-C25)/C25 -> -0.41890202 | E24: 0.061675838 | G24: 22 | H24: =_xlfn.NORM.INV(RAND(),$N$4,$N$5) -> 0.00044114541
B25: 43972 | C25: 439.9 | D25: =(C25-C26)/C26 -> -0.090692987 | E25: 0.059617006 | G25: 23 | H25: =_xlfn.NORM.INV(RAND(),$N$4,$N$5) -> 0.0075651476 | J25: Percentile | K25: Confidence | L25: VAR% | M25: Stock Price | N25: VAR (INR)
B26: 43938 | C26: 483.775 | D26: =(C26-C27)/C27 -> -0.92388089 | E26: 0.059226011 | G26: 24 | H26: =_xlfn.NORM.INV(RAND(),$N$4,$N$5) -> 0.03147412 | J26: 0.05 | K26: =100%-J26 -> 0.95 | L26: =_xlfn.PERCENTILE.INC($H$3:$H$2120,J26) -> -0.030284112 | M26: =$N$8*(1+L26) -> 3977.0958 | N26: =M26-$N$8 -> -124.20423
B27: 45516 | C27: 6355.5 | D27: =(C27-C28)/C28 -> 1.5967844 | E27: 0.05921028 | G27: 25 | H27: =_xlfn.NORM.INV(RAND(),$N$4,$N$5) -> -0.01485754 | J27: 0.01 | K27: =100%-J27 -> 0.99 | L27: =_xlfn.PERCENTILE.INC($H$3:$H$2120,J27) -> -0.040508043 | M27: =$N$8*(1+L27) -> 3935.1644 | N27: =M27-$N$8 -> -166.13564
B28: 45238 | C28: 2447.45 | D28: =(C28-C29)/C29 -> -0.45913006 | E28: 0.056825788 | G28: 26 | H28: =_xlfn.NORM.INV(RAND(),$N$4,$N$5) -> 0.0042936676 | J28: 0.005 | K28: =100%-J28 -> 0.995 | L28: =_xlfn.PERCENTILE.INC($H$3:$H$2120,J28) -> -0.047526375 | M28: =$N$8*(1+L28) -> 3906.3801 | N28: =M28-$N$8 -> -194.91992
B29: 45412 | C29: 4525.025 | D29: =(C29-C30)/C30 -> 1.4426586 | E29: 0.056335644 | G29: 27 | H29: =_xlfn.NORM.INV(RAND(),$N$4,$N$5) -> 0.016641269 | J29: 0.1 | K29: =100%-J29 -> 0.9 | L29: =_xlfn.PERCENTILE.INC($H$3:$H$2120,J29) -> -0.024078856 | M29: =$N$8*(1+L29) -> 4002.5454 | N29: =M29-$N$8 -> -98.754614
B30: 45148 | C30: 1852.5 | D30: =(C30-C31)/C31 -> 5.0038892 | E30: 0.055720982 | G30: 28 | H30: =_xlfn.NORM.INV(RAND(),$N$4,$N$5) -> 0.0049562978
B31: 42997 | C31: 308.55 | D31: =(C31-C32)/C32 -> -0.75026305 | E31: 0.055322788 | G31: 29 | H31: =_xlfn.NORM.INV(RAND(),$N$4,$N$5) -> -0.0048381752
B32: 44637 | C32: 1235.5 | D32: =(C32-C33)/C33 -> -0.84893503 | E32: 0.053978545 | G32: 30 | H32: =_xlfn.NORM.INV(RAND(),$N$4,$N$5) -> -0.019978463
B33: 45574 | C33: 8178.6 | D33: =(C33-C34)/C34 -> 11.182319 | E33: 0.053644585 | G33: 31 | H33: =_xlfn.NORM.INV(RAND(),$N$4,$N$5) -> 0.015900901
B34: 44131 | C34: 671.35 | D34: =(C34-C35)/C35 -> -0.085354223 | E34: 0.05330457 | G34: 32 | H34: =_xlfn.NORM.INV(RAND(),$N$4,$N$5) -> 0.001427752
B35: 44243 | C35: 734 | D35: =(C35-C36)/C36 -> -0.87712859 | E35: 0.053160198 | G35: 33 | H35: =_xlfn.NORM.INV(RAND(),$N$4,$N$5) -> -0.006957846
B36: 45689 | C36: 5973.725 | D36: =(C36-C37)/C37 -> 4.412331 | E36: 0.05306556 | G36: 34 | H36: =_xlfn.NORM.INV(RAND(),$N$4,$N$5) -> 0.0050671283
B37: 44503 | C37: 1103.725 | D37: =(C37-C38)/C38 -> 1.2263742 | E37: 0.052168732 | G37: 35 | H37: =_xlfn.NORM.INV(RAND(),$N$4,$N$5) -> 0.002722764
B38: 43731 | C38: 495.75 | D38: =(C38-C39)/C39 -> 0.36947514 | E38: 0.051877785 | G38: 36 | H38: =_xlfn.NORM.INV(RAND(),$N$4,$N$5) -> 0.036012153
B39: 43313 | C39: 362 | D39: =(C39-C40)/C40 -> -0.95336374 | E39: 0.050036258 | G39: 37 | H39: =_xlfn.NORM.INV(RAND(),$N$4,$N$5) -> -0.056275579
B40: 45573 | C40: 7762.2 | D40: =(C40-C41)/C41 -> 9.7842034 | E40: 0.049804232 | G40: 38 | H40: =_xlfn.NORM.INV(RAND(),$N$4,$N$5) -> -0.022401943
B41: 44088 | C41: 719.775 | D41: =(C41-C42)/C42 -> 2.4571326 | E41: 0.0489671 | G41: 39 | H41: =_xlfn.NORM.INV(RAND(),$N$4,$N$5) -> -0.013172624
... B2319: 43914 | C2319: 395 | D2319: =(C2319-C2320)/C2320 -> -0.91679481 | E2319: -0.10633484 | G2319: 2317 | H2319: =_xlfn.NORM.INV(RAND(),$N$4,$N$5) -> -0.0011926197
B2320: 45754 | C2320: 4747.3 | D2320: =(C2320-C2323)/C2323 -> #DIV/0! | E2320: -0.15471315 | G2320: 2318 | H2320: =_xlfn.NORM.INV(RAND(),$N$4,$N$5) -> 0.029825473
G2322: 2319
G5186: 5183 | H5186: =_xlfn.NORM.INV(RAND(),$N$4,$N$5) -> -0.029744498
G5187: 5184 | H5187: =_xlfn.NORM.INV(RAND(),$N$4,$N$5) -> 0.016564665
G5188: 5185 | H5188: =_xlfn.NORM.INV(RAND(),$N$4,$N$5) -> 0.0076838918
G5189: 5186 | H5189: =_xlfn.NORM.INV(RAND(),$N$4,$N$5) -> -0.011053604
G5190: 5187 | H5190: =_xlfn.NORM.INV(RAND(),$N$4,$N$5) -> -0.0055498086
G5191: 5188 | H5191: =_xlfn.NORM.INV(RAND(),$N$4,$N$5) -> -0.026752734
G5192: 5189 | H5192: =_xlfn.NORM.INV(RAND(),$N$4,$N$5) -> 0.05043234
G5193: 5190 | H5193: =_xlfn.NORM.INV(RAND(),$N$4,$N$5) -> 0.010637398
G5194: 5191 | H5194: =_xlfn.NORM.INV(RAND(),$N$4,$N$5) -> -0.0077060301
G5195: 5192 | H5195: =_xlfn.NORM.INV(RAND(),$N$4,$N$5) -> -0.006630512
G5196: 5193 | H5196: =_xlfn.NORM.INV(RAND(),$N$4,$N$5) -> 0.021942743
G5197: 5194 | H5197: =_xlfn.NORM.INV(RAND(),$N$4,$N$5) -> 0.03546484
... G10003: 10000 | H10003: =_xlfn.NORM.INV(RAND(),$N$4,$N$5) -> -0.021858997

Sheet WACC Calculation Trent Ltd  
B2: Weighted Avg Cost of Capital
B4: All Figure are in INR unless stated otherwise
B6: Peer Comp
H7: Debt / | I7: Debt / | J7: Levered | K7: Unlevered
B8: Name if the Comp | D8: Country | E8: Total Debt | F8: Total Equity | G8: Tax Rate 1 | H8: Equity | I8: Capital | J8: Beta 2 | K8: Beta 3
B10: Trent Ltd | D10: India | E10: 2206 | F10: 5915 | G10: 0.3 | H10: =E10/F10 -> 0.37295013 | I10: =E10/(E10+F10) -> 0.27164142 | J10: 0.21 | K10: =J10/(1+(1-G10)*H10) -> 0.1665259
B11: Avenue Supermarts | D11: India | E11: 820 | F11: 21428 | G11: 0.3 | H11: =E11/F11 -> 0.038267687 | I11: =E11/(E11+F11) -> 0.036857246 | J11: 0.28 | K11: =J11/(1+(1-G11)*H11) -> 0.27269521
B12: Vishal Mega Mart | D12: India | E12: 1480 | F12: 4900 | G12: 0.3 | H12: =E12/F12 -> 0.30204082 | I12: =E12/(E12+F12) -> 0.23197492 | J12: 1.05 | K12: =J12/(1+(1-G12)*H12) -> 0.86674528
B13: Aditya Bir. Fas. | D13: India | E13: 5017 | F13: 6812 | G13: 0.3 | H13: =E13/F13 -> 0.73649442 | I13: =E13/(E13+F13) -> 0.42412715 | J13: 0.1 | K13: =J13/(1+(1-G13)*H13) -> 0.065982817
B14: V-Mart Retail Ltd | D14: India | E14: 458 | F14: 810 | G14: 0.3 | H14: =E14/F14 -> 0.5654321 | I14: =E14/(E14+F14) -> 0.36119874 | J14: 1.05 | K14: =J14/(1+(1-G14)*H14) -> 0.75225544
B15: V2 Retail Ltd | D15: India | E15: 390 | F15: 720 | G15: 0.3 | H15: =E15/F15 -> 0.54166667 | I15: =E15/(E15+F15) -> 0.35135135 | J15: 1.4 | K15: =J15/(1+(1-G15)*H15) -> 1.0151057
F17: Average | G17: =AVERAGE(G10:G15) -> 0.3 | H17: =AVERAGE(H10:H15) -> 0.42614197 | I17: =AVERAGE(I10:I15) -> 0.27952514 | J17: =AVERAGE(J10:J15) -> 0.68166667 | K17: =AVERAGE(K10:K15) -> 0.5232184
F18: Median | G18: =MEDIAN(G10:G15) -> 0.3 | H18: =MEDIAN(H10:H15) -> 0.4573084 | I18: =MEDIAN(I10:I15) -> 0.31149639 | J18: =MEDIAN(J10:J15) -> 0.665 | K18: =MEDIAN(K10:K15) -> 0.51247532
B20: Cost of Debt | G20: Cost of Equity
B22: Pre-Tax Cost of Debt | E22: 0.08 | G22: Risk Free Rate 5 | K22: 0.0739
B23: Tax Rate | E23: =G18 -> 0.3 | G23: Equity Risk Premium | K23: ='[1]Rm Calculation '!G7-'WACC Calculation Trent Ltd '!K22 -> 0.094117391
B24: Post Tax Cost of Debt | E24: =E22*(1-E23) -> 0.056 | G24: Levered Beta 4 | K24: =K32 -> 0.65165411
G25: Cost of Equity | K25: =K22+(K23*K24) -> 0.13523198
B28: Capital Structure | G28: Levered Beta
C29: Amt | D29: Current | E29: Target | G29: Comps Median Unlevered Beta | K29: =K18 -> 0.51247532
B30: Debt / Total Capital | C30: =E10 -> 2206 | D30: =C30/$C$33 -> 0.27164142 | E30: =I17 -> 0.27952514 | G30: Target Debt / Equity | K30: =E32 -> 0.38797348
B31: Equity / Total Capital | C31: =F10 -> 5915 | D31: =C31/$C$33 -> 0.72835858 | E31: =E33-E30 -> 0.72047486 | G31: Tax Rate | K31: =G18 -> 0.3
B32: Debt / Equity | D32: =D30/D31 -> 0.37295013 | E32: =E30/E31 -> 0.38797348 | G32: Levered Beta (Comparable Method) | K32: =K29*(1+(1-K31)*K30) -> 0.65165411
B33: Total Capital | C33: =SUM(C30:C31) -> 8121 | D33: =SUM(D30:D31) -> 1 | E33: =D33 -> 1
B34: Notes:
B35: 1. Tax Rate considered as Marginal Tax Rate for the Country | G35: Weighted Avg Cost of Capital
B36: 2. Levered Beta is based on 5 Year Monthly Data | J36: Total Cost | K36: Total Weight
B37: 3. Unlevered Beta = Levered Beta / (1=(1-Tax Rate)* Debt/Equity) | G37: Debt | J37: =E24 -> 0.056 | K37: =E30 -> 0.27952514
B38: 4. Levered Beta = Unlevered Beta * (1+(1-Tax Rate)*Debt/Equity) | G38: Equity | J38: =K25 -> 0.13523198 | K38: =E31 -> 0.72047486
B39: 5. Risk Free Rate - 10 Years India Bond YTM | G39: WACC | K39: =SUMPRODUCT(J37:J38,K37:K38) -> 0.11308465

Sheet DCF Trent Ltd
B2: Calculation of PV of FCFF | H2: ='Historical IFS Trent Ltd'!L3 -> 46110 | I2: =H2+366 -> 46476 | J2: =I2+366 -> 46842 | K2: =J2+366 -> 47208 | L2: =K2+365 -> 47573 | M2: =L2+365 -> 47938
B4: EBIT | H4: ='Historical IFS Trent Ltd'!L27+'Historical IFS Trent Ltd'!L21 -> 2312.2 | I4: =H4*(1+$D$13) -> 2532.3214 | J4: =I4*(1+$D$13) -> 2773.3984 | K4: =J4*(1+$D$13) -> 3037.426 | L4: =K4*(1+$D$13) -> 3326.5889 | M4: =L4*(1+$D$13) -> 3643.2802
B5: Tax Rate | H5: 0.3 | I5: =H5 -> 0.3 | J5: =I5 -> 0.3 | K5: =J5 -> 0.3 | L5: =K5 -> 0.3 | M5: =L5 -> 0.3
B6: EBIT(1-T) | H6: =H4-(H4*H5) -> 1618.54 | I6: =I4-(I4*I5) -> 1772.625 | J6: =J4-(J4*J5) -> 1941.3789 | K6: =K4-(K4*K5) -> 2126.1982 | L6: =L4-(L4*L5) -> 2328.6122 | M6: =M4-(M4*M5) -> 2550.2961
B7: Less: Reinvestment Rate | H7: ='Historical IFS Trent Ltd'!L44 -> 0.86903666 | I7: =H7+(($M$7-$H$7)/4) -> 0.83927749 | J7: =I7+(($M$7-$H$7)/4) -> 0.80951833 | K7: =J7+(($M$7-$H$7)/4) -> 0.77975916 | L7: =K7+(($M$7-$H$7)/4) -> 0.75 | M7: 0.75
B8: Free Cash Flow to Firm (FCFF) | H8: =H6*(1-H7) -> 211.96941 | I8: =I6*(1-I7) -> 284.90074 | J8: =J6*(1-J7) -> 369.7971 | K8: =K6*(1-K7) -> 468.27567 | L8: =L6*(1-L7) -> 582.15306 | M8: =M6*(1-M7) -> 637.57403
B9: Mid Year Convention | H9: 0.5 | I9: =H9+1 -> 1.5 | J9: =I9+1 -> 2.5 | K9: =J9+1 -> 3.5 | L9: =K9+1 -> 4.5 | M9: =L9+1 -> 5.5
B10: Discounting Factor | I10: =1/(1+$D$15)^I9 -> 0.8515452 | J10: =1/(1+$D$15)^J9 -> 0.76503184 | K10: =1/(1+$D$15)^K9 -> 0.68730787 | L10: =1/(1+$D$15)^L9 -> 0.61748032 | M10: =1/(1+$D$15)^M9 -> 0.55474696
B11: PV of FCFF | I11: =I10*I8 -> 242.60586 | J11: =J10*J8 -> 282.90656 | K11: =K10*K8 -> 321.84955 | L11: =L10*L8 -> 359.46806 | M11: =M10*M8 -> 353.69225
B13: Expected Growth | D13: 0.0952
B14: Terminal Growth | D14: 0.065
B15: WACC | D15: ='WACC Calculation Trent Ltd '!K39 -> 0.11308465
B17: Calculation of Terminal Value
B18: FCFF(n+1) | H18: =M8*(1+D13) -> 698.27108
B19: WACC | H19: =D15 -> 0.11308465
B20: Terminal Growth Rate | H20: =D14 -> 0.065
B21: Terminal Value | H21: =H18/(H19-H20) -> 14521.704
B23: Calculation of Equity Value
B24: PV of FCFF | H24: =SUM(I11:M11) -> 1560.5223
B25: PV of Terminal Value | H25: =H21*M10 -> 8055.8709
B26: Value of Operating Assets | H26: =SUM(H24:H25) -> 9616.3931
B28: Add: Cash | H28: ='Historical IFS Trent Ltd'!L61 -> 283
B29: Less: Debt | H29: ='Historical IFS Trent Ltd'!L49 -> 2561.25
B30: Value of Equity | H30: =(H26+H28)-H29 -> 7338.1431
B31: No of Shares | H31: ='Raw Data Trent Ltd'!K93 -> 35.55
B32: Equity Value per Share | H32: =H30/H31 -> 206.41753
B34: Actual Share price | H34: 4101.3
B35: Discount/Premium | H35: =H34/H32 -> 19.868952
B37: Scenario Analysis of Terminal Value
B38: =H21 -> 14521.704 | C38: 0.1 | D38: 0.11 | E38: 0.1131 | F38: 0.12 | G38: 0.13 | H38: WACC
B39: 0.03 | C39: 9975.3012 | D39: 8728.3885 | E39: 8402.7808 | F39: 7758.5676 | G39: 6982.7108
B40: 0.04 | C40: 11637.851 | D40: 9975.3012 | E40: 9552.272 | F40: 8728.3885 | G40: 7758.5676
B41: 0.05 | C41: 13965.422 | D41: 11637.851 | E41: 11066.103 | F41: 9975.3012 | G41: 8728.3885
B42: 0.0538 | C42: 15114.093 | D42: 12424.752 | E42: 11775.229 | F42: 10547.902 | G42: 9163.6625
B43: 0.06 | C43: 17456.777 | D43: 13965.422 | E43: 13150.115 | F43: 11637.851 | G43: 9975.3012
B44: 0.07 | C44: 23275.703 | D44: 17456.777 | E44: 16201.185 | F44: 13965.422 | G44: 11637.851
B45: Terminal Growth Rate

Sheet Forecasting Trent Ltd
A2: # | B2: ="Forecasting - "&'Historical IFS Trent Ltd'!B6&" ("&'Raw Data Trent Ltd'!B1&")." -> Forecasting - Sales (TRENT LTD). | G2: SUMMARY OUTPUT
B3: Year Weight | C3: Year | D3: Sales | E3: Sales Growth %
B4: 1 | C4: ='Historical IFS Trent Ltd'!$C$3 -> 42825 | D4: {=TRANSPOSE('Historical IFS Trent Ltd'!C6:M6)} -> 1812.44 | G4: Regression Statistics
B5: 2 | C5: =C4+365 -> 43190 | D5: 2157.46 | E5: =D5/D4-1 -> 0.19036216 | G5: Multiple R | H5: 0.90931874
B6: 3 | C6: =C5+365 -> 43555 | D6: 2630.24 | E6: =D6/D5-1 -> 0.21913732 | G6: R Square | H6: 0.82686058
B7: 4 | C7: =C6+365 -> 43920 | D7: 3485.98 | E7: =D7/D6-1 -> 0.32534674 | G7: Adjusted R Square | H7: 0.80521815
B8: 5 | C8: =C7+365 -> 44285 | D8: 2592.96 | E8: =D8/D7-1 -> -0.25617473 | G8: Standard Error | H8: 2975.4175
B9: 6 | C9: =C8+365 -> 44650 | D9: 4498.02 | E9: =D9/D8-1 -> 0.73470474 | G9: Observations | H9: 10
B10: 7 | C10: =C9+365 -> 45015 | D10: 8242.02 | E10: =D10/D9-1 -> 0.83236624 | G10: ANOVA
B11: 8 | C11: =C10+365 -> 45380 | D11: 12375.11 | E11: =D11/D10-1 -> 0.50146566 | H11: df | I11: SS | J11: MS | K11: F | L11: Significance F
B12: 9 | C12: =C11+365 -> 45745 | D12: 17134.61 | E12: =D12/D11-1 -> 0.38460264 | G12: Regression | H12: 1 | I12: 3.382378e+08 | J12: 3.382378e+08 | K12: 38.205537 | L12: 0.00026484272
B13: 10 | C13: =C12+365 -> 46110 | D13: 20074.21 | E13: =D13/D12-1 -> 0.1715592 | G13: Residual | H13: 8 | I13: 70824876 | J13: 8853109.5
B14: 11 | C14: =C13+365 -> 46475 | D14: =$H$16+B14*$H$17 -> 18636.755 | E14: =D14/D13-1 -> -0.071607035 | G14: Total | H14: 9 | I14: 4.0906267e+08
B15: 12 | C15: =C14+365 -> 46840 | D15: =$H$16+B15*$H$17 -> 20661.564 | E15: =D15/D14-1 -> 0.10864601 | H15: Coefficients | I15: Standard Error | J15: t Stat | K15: P-value | L15: Lower 95% | M15: Upper 95% | N15: Lower 95.0% | O15: Upper 95.0%
B16: 13 | C16: =C15+365 -> 47205 | D16: =$H$16+B16*$H$17 -> 22686.374 | E16: =D16/D15-1 -> 0.09799883 | G16: Intercept | H16: -3636.1453 | I16: 2032.5971 | J16: -1.7889159 | K16: 0.11142382 | L16: -8323.3227 | M16: 1051.0321 | N16: -8323.3227 | O16: 1051.0321
B17: 14 | C17: =C16+365 -> 47570 | D17: =$H$16+B17*$H$17 -> 24711.183 | E17: =D17/D16-1 -> 0.089252217 | G17: Year Weight | H17: 2024.8092 | I17: 327.58269 | J17: 6.1810627 | K17: 0.00026484272 | L17: 1269.4021 | M17: 2780.2162 | N17: 1269.4021 | O17: 2780.2162
A21: # | B21: ="Forecasting - "&'Historical IFS Trent Ltd'!B18&" ("&'Raw Data Trent Ltd'!B1&")." -> Forecasting - EBITDA (TRENT LTD). | G21: SUMMARY OUTPUT
B22: Year Weight | C22: Year | D22: EBITDA | E22: EBITDA Growth %
B23: 1 | C23: ='Historical IFS Trent Ltd'!$C$3 -> 42825 | D23: {=TRANSPOSE('Historical IFS Trent Ltd'!C18:M18)} -> 133.53 | G23: Regression Statistics
B24: 2 | C24: =C23+365 -> 43190 | D24: 208.5 | E24: =D24/D23-1 -> 0.56144687 | G24: Multiple R | H24: 0.8869864
B25: 3 | C25: =C24+365 -> 43555 | D25: 240.64 | E25: =D25/D24-1 -> 0.15414868 | G25: R Square | H25: 0.78674487
B26: 4 | C26: =C25+365 -> 43920 | D26: 528.97 | E26: =D26/D25-1 -> 1.1981799 | G26: Adjusted R Square | H26: 0.76008797
B27: 5 | C27: =C26+365 -> 44285 | D27: 113.87 | E27: =D27/D26-1 -> -0.78473259 | G27: Standard Error | H27: 618.36213
B28: 6 | C28: =C27+365 -> 44650 | D28: 594.72 | E28: =D28/D27-1 -> 4.2227979 | G28: Observations | H28: 10
B29: 7 | C29: =C28+365 -> 45015 | D29: 1114.15 | E29: =D29/D28-1 -> 0.87340261 | G29: ANOVA
B30: 8 | C30: =C29+365 -> 45380 | D30: 1970.69 | E30: =D30/D29-1 -> 0.76878338 | H30: df | I30: SS | J30: MS | K30: F | L30: Significance F
B31: 9 | C31: =C30+365 -> 45745 | D31: 2819.96 | E31: =D31/D30-1 -> 0.43095058 | G31: Regression | H31: 1 | I31: 11285224 | J31: 11285224 | K31: 29.513751 | L31: 0.00062137368
B32: 10 | C32: =C31+365 -> 46110 | D32: 3673.39 | E32: =D32/D31-1 -> 0.30263904 | G32: Residual | H32: 8 | I32: 3058973.8 | J32: 382371.72
B33: 11 | C33: =C32+365 -> 46475 | D33: =$H$35+B33*$H$36 -> 3174.0287 | E33: =D33/D32-1 -> -0.13594019 | G33: Total | H33: 9 | I33: 14344198
B34: 12 | C34: =C33+365 -> 46840 | D34: =$H$35+B34*$H$36 -> 3543.8808 | E34: =D34/D33-1 -> 0.11652451 | H34: Coefficients | I34: Standard Error | J34: t Stat | K34: P-value | L34: Lower 95% | M34: Upper 95% | N34: Lower 95.0% | O34: Upper 95.0%
B35: 13 | C35: =C34+365 -> 47205 | D35: =$H$35+B35*$H$36 -> 3913.7329 | E35: =D35/D34-1 -> 0.10436359 | G35: Intercept | H35: -894.34467 | I35: 422.42175 | J35: -2.1171842 | K35: 0.067118704 | L35: -1868.451 | M35: 79.761641 | N35: -1868.451 | O35: 79.761641
B36: 14 | C36: =C35+365 -> 47570 | D36: =$H$35+B36*$H$36 -> 4283.585 | E36: =D36/D35-1 -> 0.094501114 | G36: Year Weight | H36: 369.85212 | I36: 68.07943 | J36: 5.432656 | K36: 0.00062137368 | L36: 212.86067 | M36: 526.84357 | N36: 212.86067 | O36: 526.84357
A40: # | B40: ="Forecasting - "&'Historical IFS Trent Ltd'!B38&" ("&'Raw Data Trent Ltd'!B1&")." -> Forecasting - EPS (TRENT LTD). | G40: SUMMARY OUTPUT
B41: Year Weight | C41: Year | D41: EPS | E41: EPS Growth %
B42: 1 | C42: ='Historical IFS Trent Ltd'!$C$3 -> 42825 | D42: {=TRANSPOSE('Historical IFS Trent Ltd'!C38:L38)} -> 0.10953957 | G42: Regression Statistics
B43: 2 | C43: =C42+365 -> 43190 | D43: 1.7926572 | E43: =D43/D42-1 -> 15.365385 | G43: Multiple R | H43: 0.7299409
B44: 3 | C44: =C43+365 -> 43555 | D44: 1.9476377 | E44: =D44/D43-1 -> 0.086452913 | G44: R Square | H44: 0.53281371
B45: 4 | C45: =C44+365 -> 43920 | D45: -1.1434599 | E45: =D45/D44-1 -> -1.5871009 | G45: Adjusted R Square | H45: 0.47441542
B46: 5 | C46: =C45+365 -> 44285 | D46: -10.704079 | E46: =D46/D45-1 -> 8.3611316 | G46: Standard Error | H46: 13.033031
B47: 6 | C47: =C46+365 -> 44650 | D47: -3.3068917 | E47: =D47/D46-1 -> -0.69106247 | G47: Observations | H47: 10
B48: 7 | C48: =C47+365 -> 45015 | D48: 1.4917018 | E48: =D48/D47-1 -> -1.4510888 | G48: ANOVA
B49: 8 | C49: =C48+365 -> 45380 | D49: 13.742616 | E49: =D49/D48-1 -> 8.2127098 | H49: df | I49: SS | J49: MS | K49: F | L49: Significance F
B50: 9 | C50: =C49+365 -> 45745 | D50: 34.580872 | E50: =D50/D49-1 -> 1.5163238 | G50: Regression | H50: 1 | I50: 1549.7661 | J50: 1549.7661 | K50: 9.1237902 | L50: 0.016545341
B51: 10 | C51: =C50+365 -> 46110 | D51: 45.814346 | E51: =D51/D50-1 -> 0.32484646 | G51: Residual | H51: 8 | I51: 1358.8792 | J51: 169.85991
B52: 11 | C52: =C51+365 -> 46475 | D52: =$H$54+B52*$H$55 -> 32.270438 | E52: =D52/D51-1 -> -0.29562591 | G52: Total | H52: 9 | I52: 2908.6454
B53: 12 | C53: =C52+365 -> 46840 | D53: =$H$54+B53*$H$55 -> 36.60461 | E53: =D53/D52-1 -> 0.1343078 | H53: Coefficients | I53: Standard Error | J53: t Stat | K53: P-value | L53: Lower 95% | M53: Upper 95% | N53: Lower 95.0% | O53: Upper 95.0%
B54: 13 | C54: =C53+365 -> 47205 | D54: =$H$54+B54*$H$55 -> 40.938782 | E54: =D54/D53-1 -> 0.11840508 | G54: Intercept | H54: -15.40545 | I54: 8.9032553 | J54: -1.7303166 | K54: 0.12182331 | L54: -35.936394 | M54: 5.1254935 | N54: -35.936394 | O54: 5.1254935
B55: 14 | C55: =C54+365 -> 47570 | D55: =$H$54+B55*$H$55 -> 45.272953 | E55: =D55/D54-1 -> 0.10586958 | G55: Year Weight | H55: 4.3341717 | I55: 1.4348895 | J55: 3.0205612 | K55: 0.016545341 | L55: 1.0253105 | M55: 7.6430328 | N55: 1.0253105 | O55: 7.6430328

Sheet Raw Data CF Trent Ltd
C2: 42064 | D2: 42430 | E2: 42795 | F2: 43160 | G2: 43525 | H2: 43891 | I2: 44256 | J2: 44621 | K2: 44986 | L2: 45352 | M2: 45717 | N2: 46082
B3: Cash from Operating Activity - | C3: -10 | D3: 109 | E3: 102 | F3: 77 | G3: 21 | H3: 361 | I3: 285 | J3: 58 | K3: 595 | L3: 1349 | M3: 1661 | N3: 2668
B4: Profit from operations | C4: 65 | D4: 98 | E4: 165 | F4: 191 | G4: 233 | H4: 542 | I4: 180 | J4: 569 | K4: 1079 | L4: 1919 | M4: 2723 | N4: 3618
B5: Receivables | C5: -19 | D5: -1 | E5: 24 | F5: -54 | G5: -11 | H5: -20 | I5: -39 | J5: -103 | K5: -101 | L5: -208 | M5: -203 | N5: -196
B6: Inventory | C6: -3 | D6: -19 | E6: -26 | F6: -39 | G6: -152 | H6: -89 | I6: 179 | J6: -439 | K6: -494 | L6: -222 | M6: -462 | N6: -243
B7: Payables | C7: -6 | D7: 27 | E7: -9 | F7: 43 | G7: 49 | H7: 26 | I7: -11 | J7: 134 | K7: 332 | L7: 178 | M7: 212 | N7: 311
B8: Loans Advances | C8: 0 | D8: 0 | E8: 0 | F8: 0 | G8: 0 | H8: 0 | I8: 0 | J8: 0 | K8: 0 | L8: 0 | M8: 0 | N8: -288
B9: Other WC items | C9: -34 | D9: 24 | E9: -12 | F9: -13 | G9: -21 | H9: -15 | I9: -23 | J9: -22 | K9: -30 | L9: -20 | M9: -115 | N9: 17
B10: Working capital changes | C10: -61 | D10: 31 | E10: -24 | F10: -64 | G10: -135 | H10: -97 | I10: 106 | J10: -430 | K10: -293 | L10: -272 | M10: -568 | N10: -399
B11: Direct taxes | C11: -13 | D11: -20 | E11: -38 | F11: -50 | G11: -77 | H11: -83 | I11: -1 | J11: -82 | K11: -191 | L11: -299 | M11: -494 | N11: -551
B12: Cash from Investing Activity - | C12: -306 | D12: -98 | E12: -44 | F12: -4 | G12: -37 | H12: -809 | I12: 18 | J12: 56 | K12: -103 | L12: -508 | M12: -923 | N12: -1578
B13: Fixed assets purchased | C13: -158 | D13: -139 | E13: -71 | F13: -107 | G13: -203 | H13: -156 | I13: -113 | J13: -271 | K13: -503 | L13: -737 | M13: -1268 | N13: -1763
B14: Fixed assets sold | C14: 2 | D14: 8 | E14: 2 | F14: 1 | G14: 7 | H14: 42 | I14: 22 | J14: 61 | K14: 280 | L14: 343 | M14: 407 | N14: 26
... B33: CFO/OP | C33: 0.04 | D33: 1.44 | E33: 1.05 | F33: 0.61 | G33: 0.41 | H33: 0.84 | I33: 2.51 | J33: 0.23 | K33: 0.71 | L33: 0.84 | M33: 0.76 | N33: 0.88

Sheet Raw Data Trent Ltd
A1: COMPANY NAME | B1: TRENT LTD
A2: LATEST VERSION | B2: 2.1 | E2: PLEASE DO NOT MAKE ANY CHANGES TO THIS SHEET
A3: CURRENT VERSION | B3: 2.1
A5: META
A6: Number of shares
A7: Face Value | B7: 1
A8: Current Price | B8: 4289.8
A9: Market Capitalization | B9: 152655.74
A15: PROFIT & LOSS
A16: Report Date | B16: 42825 | C16: 43190 | D16: 43555 | E16: 43921 | F16: 44286 | G16: 44651 | H16: 45016 | I16: 45382 | J16: 45747 | K16: 46112
A17: Sales | B17: 1812.44 | C17: 2157.46 | D17: 2630.24 | E17: 3485.98 | F17: 2592.96 | G17: 4498.02 | H17: 8242.02 | I17: 12375.11 | J17: 17134.61 | K17: 20074.21
A18: Raw Material Cost | B18: 911.22 | C18: 1070.02 | D18: 1459.67 | E18: 1951.64 | F18: 1371.64 | G18: 2920.38 | H18: 5211.05 | I18: 7123.6 | J18: 10143.39 | K18: 11496.89
A19: Change in Inventory | B19: 29.86 | C19: 38.51 | D19: 148.23 | E19: 69.89 | F19: -162.36 | G19: 438.84 | H19: 491.31 | I19: 164.71 | J19: 454.25 | K19: 232.18
A20: Power and Fuel | B20: 51.28 | C20: 52.75 | D20: 59.18 | E20: 66.64 | F20: 49.41 | G20: 71.89 | H20: 144.28 | I20: 229.16 | J20: 349.87
A21: Other Mfr. Exp | B21: 81.91 | C21: 90.78 | D21: 122.09 | E21: 97.51 | F21: 92 | G21: 127.14 | H21: 211.99 | I21: 264.59 | J21: 369.79
A22: Employee Cost | B22: 194.72 | C22: 233.02 | D22: 288.89 | E22: 361.01 | F22: 303.4 | G22: 402.92 | H22: 659.07 | I22: 1041.74 | J22: 1315.54 | K22: 1355.49
A23: Selling and admin | B23: 407.07 | C23: 450.61 | D23: 514.41 | E23: 436.82 | F23: 364.62 | G23: 705.03 | H23: 1252.53 | I23: 1709.55 | J23: 2322.83 | K23: 1563.94
A24: Other Expenses | B24: 62.57 | C24: 90.29 | D24: 93.59 | E24: 113.28 | F24: 135.66 | G24: 114.78 | H24: 140.26 | I24: 200.49 | J24: 267.48 | K24: 2216.68
A25: Other Income | B25: 81.31 | C25: 27.47 | D25: 30.14 | E25: 146.63 | F25: 199.4 | G25: 152.16 | H25: 340.6 | I25: 988.91 | J25: 305.06 | K25: 92.63
A26: Depreciation | B26: 41.29 | C26: 45.53 | D26: 51.67 | E26: 247.24 | F26: 257.3 | G26: 310.82 | H26: 493.69 | I26: 671.11 | J26: 895.18 | K26: 1361.19
A27: Interest | B27: 45.55 | C27: 43.78 | D27: 50.64 | E27: 263.37 | F27: 260.79 | G27: 324.84 | H27: 408.99 | I27: 367.66 | J27: 200.1 | K27: 168.35
A28: Profit before tax | B28: 128 | C28: 146.66 | D28: 168.47 | E28: 164.99 | F28: -204.82 | G28: 111.22 | H28: 552.07 | I28: 1920.83 | J28: 2029.74 | K28: 2236.48
A29: Tax | B29: 43.05 | C29: 59.62 | D29: 73.61 | E29: 59.01 | F29: -23.69 | G29: 76.62 | H29: 158.44 | I29: 443.37 | J29: 495.33 | K29: 515.15
A30: Net profit | B30: 84.86 | C30: 86.97 | D30: 96.96 | E30: 122.85 | F30: -146.17 | G30: 105.83 | H30: 444.63 | I30: 1486.8 | J30: 1546.72 | K30: 1719.65
A31: Dividend Amount | B31: 33.23 | C31: 38.21 | D31: 43.2 | E31: 35.55 | F31: 21.33 | G31: 60.44 | H31: 78.21 | I31: 113.76 | J31: 177.75 | K31: 213.3
A32: Effective Tax Rate | B32: =B29/B28 -> 0.33632812 | C32: =C29/C28 -> 0.40651848 | D32: =D29/D28 -> 0.43693239 | E32: =E29/E28 -> 0.35765804 | F32: =F29/F28 -> 0.11566253 | G32: =G29/G28 -> 0.68890487 | H32: =H29/H28 -> 0.28699259 | I32: =I29/I28 -> 0.23082209 | ... K32: =K29/K28 -> 0.23033964
A34: EBITDA | B34: =+B30+B29+B27+B26 -> 214.75 | C34: =+C30+C29+C27+C26 -> 235.9 | D34: =+D30+D29+D27+D26 -> 272.88 | E34: =+E30+E29+E27+E26 -> 692.47 | F34: =+F30+F29+F27+F26 -> 348.23 | G34: =+G30+G29+G27+G26 -> 818.11 | H34: =+H30+H29+H27+H26 -> 1505.75 | I34: =+I30+I29+I27+I26 -> 2968.94 | ... K34: =+K30+K29+K27+K26 -> 3764.34
A40: Quarters
A41: Report Date | B41: 45291 | C41: 45382 | D41: 45473 | E41: 45565 | F41: 45657 | G41: 45747 | H41: 45838 | I41: 45930 | J41: 46022 | K41: 46112
A42: Sales | B42: 3466.62 | C42: 3297.7 | D42: 4104.44 | E42: 4156.67 | F42: 4656.56 | G42: 4216.94 | H42: 4883.48 | I42: 4817.68 | J42: 5345.06 | K42: 5027.99
A43: Expenses | B43: 2838.1 | C43: 2828.06 | D43: 3491.09 | E43: 3510.95 | F43: 3809.19 | G43: 3566.03 | H43: 4035.62 | I43: 4001.7 | J43: 4263.99 | K43: 4116.69
A44: Other Income | B44: 110.01 | C44: 694.87 | D44: 100.91 | E44: 51.04 | F44: 79.87 | G44: 74.34 | H44: 49.8 | I44: 27.55 | J44: 4.55 | K44: 27.91
A45: Depreciation | B45: 164.53 | C45: 212.94 | D45: 181.32 | E45: 196.95 | F45: 244.93 | G45: 271.98 | H45: 292.93 | I45: 324.93 | J45: 366.74 | K45: 376.59
A46: Interest | B46: 98.81 | C46: 32.54 | D46: 31.55 | E46: 33 | F46: 36.52 | G46: 37.52 | H46: 40.04 | I46: 41.62 | J46: 42.94 | K46: 43.75
A47: Profit before tax | B47: 475.19 | C47: 919.03 | D47: 501.39 | E47: 466.81 | F47: 645.79 | G47: 415.75 | H47: 564.69 | I47: 476.98 | J47: 675.94 | K47: 518.87
A48: Tax | B48: 104.55 | C48: 206.94 | D48: 110.18 | E48: 131.75 | F48: 149.25 | G48: 104.15 | H48: 139.99 | I48: 103.56 | J48: 165.83 | K48: 105.77
A49: Net profit | B49: 374.36 | C49: 704.23 | D49: 392.57 | E49: 338.75 | F49: 497.25 | G49: 318.15 | H49: 429.69 | I49: 376.86 | J49: 512.77 | K49: 400.33
A50: Operating Profit | B50: 628.52 | C50: 469.64 | D50: 613.35 | E50: 645.72 | F50: 847.37 | G50: 650.91 | H50: 847.86 | I50: 815.98 | J50: 1081.07 | K50: 911.3
A51: EBITDA | B51: =B49+B48+B46+B45 -> 742.25 | C51: =C49+C48+C46+C45 -> 1156.65 | D51: =D49+D48+D46+D45 -> 715.62 | E51: =E49+E48+E46+E45 -> 700.45 | F51: =F49+F48+F46+F45 -> 927.95 | G51: =G49+G48+G46+G45 -> 731.8 | H51: =H49+H48+H46+H45 -> 902.65 | I51: =I49+I48+I46+I45 -> 846.97 | ... K51: =K49+K48+K46+K45 -> 926.44
A55: BALANCE SHEET
A56: Report Date | B56: 42460 | C56: 42825 | D56: 43190 | E56: 43555 | F56: 43921 | G56: 44286 | H56: 44651 | I56: 45016 | J56: 45382 | K56: 45747
A57: Equity Share Capital | B57: 33.23 | C57: 33.23 | D57: 33.23 | E57: 35.55 | F57: 35.55 | G57: 35.55 | H57: 35.55 | I57: 35.55 | J57: 35.55 | K57: 35.55
A58: Reserves | B58: 1514.46 | C58: 1562.14 | D58: 1613.28 | E58: 2352.22 | F58: 2277.48 | G58: 2328.45 | H58: 2559.94 | I58: 4032.19 | J58: 5426.19 | K58: 6949.13
A59: Borrowings | B59: 391.74 | C59: 391.43 | D59: 494.14 | E59: 299.74 | F59: 2963.63 | G59: 4725.36 | H59: 4464.14 | I59: 1752.99 | J59: 2237.19 | K59: 2561.25
A60: Other Liabilities | B60: 282.82 | C60: 349.06 | D60: 418.11 | E60: 2819.17 | F60: 447.07 | G60: 636.66 | H60: 1021.9 | I60: 1341.02 | J60: 1720.71 | K60: 2182.65
A61: Total | B61: 2222.25 | C61: 2335.86 | D61: 2558.76 | E61: 5506.68 | F61: 5723.73 | G61: 7726.02 | H61: 8081.53 | I61: 7161.75 | J61: 9419.64 | K61: 11728.58
A62: Net Block | B62: 548.71 | C62: 612.53 | D62: 662.18 | E62: 2738.43 | F62: 3053.82 | G62: 4686.71 | H62: 4526.95 | I62: 2449.92 | J62: 3895.13 | K62: 5518.74
A63: Capital Work in Progress | B63: 5.48 | C63: 9.59 | D63: 87.18 | E63: 23.32 | F63: 107.98 | G63: 104.72 | H63: 101.72 | I63: 223.78 | J63: 179.5 | K63: 253.99
A64: Investments | B64: 1079.96 | C64: 1022.88 | D64: 882.83 | E64: 1514.78 | F64: 1487.29 | G64: 1283.72 | H64: 1109.87 | I64: 1416.03 | J64: 1480.25 | K64: 1384.91
A65: Other Assets | B65: 588.1 | C65: 690.86 | D65: 926.57 | E65: 1230.15 | F65: 1074.64 | G65: 1650.87 | H65: 2342.99 | I65: 3072.02 | J65: 3864.76 | K65: 4570.94
A66: Total | B66: 2222.25 | C66: 2335.86 | D66: 2558.76 | E66: 5506.68 | F66: 5723.73 | G66: 7726.02 | H66: 8081.53 | I66: 7161.75 | J66: 9419.64 | K66: 11728.58
A67: Receivables | B67: 5.92 | C67: 15.1 | D67: 16.54 | E67: 17.12 | F67: 20.77 | G67: 18.26 | H67: 34.39 | I67: 81.74 | J67: 62.95 | K67: 51.14
... A69: Cash & Bank | B69: 34.28 | C69: 32.81 | D69: 54.23 | E69: 61.41 | F69: 81.47 | G69: 85.97 | H69: 86.3 | I69: 297.56 | J69: 339.84 | K69: 283
A70: No. of Equity Shares | B70: 332316730 | C70: 332316730 | D70: 332316730 | E70: 355487461 | F70: 355487461 | G70: 355487461 | H70: 355487461 | I70: 355487461 | J70: 355487461
A71: New Bonus Shares
A72: Face value | B72: 1 | C72: 1 | D72: 1 | E72: 1 | F72: 1 | G72: 1 | H72: 1 | I72: 1 | J72: 1 | K72: 1
H73: =H62-G62+H45 -> 133.17 | I73: =I62-H62+I45 -> -1752.1 | J73: =J62-I62+J45 -> 1811.95 | K73: =K62-J62+K45 -> 2000.2
A75: Other Asset | B75: =B65-SUM(B67:B69) -> 242.54 | C75: =C65-SUM(C67:C69) -> 298.18 | D75: =D65-SUM(D67:D69) -> 358.79 | E75: =E65-SUM(E67:E69) -> 543.81 | F75: =F65-SUM(F67:F69) -> 544.01 | G75: =G65-SUM(G67:G69) -> 678.86 | H75: =H65-SUM(H67:H69) -> 861.14 | I75: =I65-SUM(I67:I69) -> 1109.99 | ... K75: =K65-SUM(K67:K69) -> 1947.79
A77: Total Assets | B77: =B61 -> 2222.25 | C77: =C61 -> 2335.86 | D77: =D61 -> 2558.76 | E77: =E61 -> 5506.68 | F77: =F61 -> 5723.73 | G77: =G61 -> 7726.02 | H77: =H61 -> 8081.53 | I77: =I61 -> 7161.75 | ... K77: =K61 -> 11728.58
A80: CASH FLOW:
A81: Report Date | B81: 42825 | C81: 43190 | D81: 43555 | E81: 43921 | F81: 44286 | G81: 44651 | H81: 45016 | I81: 45382 | J81: 45747 | K81: 46112
A82: Cash from Operating Activity | B82: 102.44 | C82: 76.86 | D82: 20.98 | E82: 361.16 | F82: 285.03 | G82: 58.08 | H82: 594.88 | I82: 1348.98 | J82: 1660.9 | K82: 2667.62
A83: Cash from Investing Activity | B83: -43.7 | C83: -4.02 | D83: -37.03 | E83: -808.56 | F83: 17.71 | G83: 56.03 | H83: -102.63 | I83: -508.21 | J83: -923.31 | K83: -1578.36
A84: Cash from Financing Activity | B84: -51.36 | C84: -74.31 | D84: 37.47 | E84: 451.94 | F84: -283.11 | G84: -107.98 | H84: -491.41 | I84: -629.45 | J84: -693.67 | K84: -1147.61
A85: Net Cash Flow | B85: 7.38 | C85: -1.47 | D85: 21.42 | E85: 4.54 | F85: 19.63 | G85: 6.13 | H85: 0.84 | I85: 211.32 | J85: 43.92 | K85: -58.35
A90: PRICE: | B90: 266.7 | C90: 345.05 | D90: 361.9 | E90: 484.35 | F90: 751.05 | G90: 1275.5 | H90: 1374.95 | I90: 3948 | J90: 5325.15 | K90: 3295.8
A92: DERIVED:
A93: Adjusted Equity Shares in Cr | B93: 33.23 | C93: 33.23 | D93: 33.23 | E93: 35.55 | F93: 35.55 | G93: 35.55 | H93: 35.55 | I93: 35.55 | J93: 35.55 | K93: 35.55
